{
  "edges": [
    {
      "from": "atlas",
      "relation": "ingests",
      "to": "source:airtable"
    },
    {
      "from": "atlas",
      "relation": "ingests",
      "to": "source:changelog"
    },
    {
      "from": "atlas",
      "relation": "ingests",
      "to": "source:clay"
    },
    {
      "from": "atlas",
      "relation": "ingests",
      "to": "source:ghl"
    },
    {
      "from": "atlas",
      "relation": "ingests",
      "to": "source:make"
    },
    {
      "from": "atlas",
      "relation": "ingests",
      "to": "source:models"
    },
    {
      "from": "atlas",
      "relation": "ingests",
      "to": "source:qb"
    },
    {
      "from": "atlas",
      "relation": "ingests",
      "to": "source:root"
    },
    {
      "from": "atlas",
      "relation": "ingests",
      "to": "source:snapshots"
    },
    {
      "from": "atlas",
      "relation": "ingests",
      "to": "source:softr"
    },
    {
      "from": "atlas",
      "relation": "ingests",
      "to": "source:videoask"
    },
    {
      "from": "atlas",
      "relation": "ingests",
      "to": "source:videopeel"
    },
    {
      "from": "atlas",
      "relation": "ingests",
      "to": "source:web"
    },
    {
      "from": "source:root",
      "relation": "contains",
      "to": "file:inputs/README.md"
    },
    {
      "from": "source:airtable",
      "relation": "contains",
      "to": "file:inputs/airtable/Airtable \u00b7 Dancing King Client Vault \u00b7 System Map \u00b7 v0.md"
    },
    {
      "from": "source:airtable",
      "relation": "contains",
      "to": "file:inputs/airtable/AirtableSchema__DancingKingClientVault__2026-02-12T14_19_55.058Z.json.docx"
    },
    {
      "from": "source:airtable",
      "relation": "contains",
      "to": "file:inputs/airtable/AirtableSchema__DancingKingClientVault__Latest.json"
    },
    {
      "from": "source:airtable",
      "relation": "contains",
      "to": "file:inputs/airtable/AirtableSchema__app0ezVqvqQRWTXIJ__Latest.json"
    },
    {
      "from": "source:airtable",
      "relation": "contains",
      "to": "file:inputs/airtable/AirtableSchema__appQFyu6Aejoq7yHP__Latest.json"
    },
    {
      "from": "source:airtable",
      "relation": "contains",
      "to": "file:inputs/airtable/README.md"
    },
    {
      "from": "source:changelog",
      "relation": "contains",
      "to": "file:inputs/changelog/index.md"
    },
    {
      "from": "source:clay",
      "relation": "contains",
      "to": "file:inputs/clay/README.md"
    },
    {
      "from": "source:ghl",
      "relation": "contains",
      "to": "file:inputs/ghl/GHLCalendars__JH4o9LqPhHyuvvyVFJVZ__Latest.json"
    },
    {
      "from": "source:ghl",
      "relation": "contains",
      "to": "file:inputs/ghl/GHLContacts__JH4o9LqPhHyuvvyVFJVZ__Latest.json"
    },
    {
      "from": "source:ghl",
      "relation": "contains",
      "to": "file:inputs/ghl/GHLConversations__JH4o9LqPhHyuvvyVFJVZ__Latest.json"
    },
    {
      "from": "source:ghl",
      "relation": "contains",
      "to": "file:inputs/ghl/GHLCustomFields__JH4o9LqPhHyuvvyVFJVZ__Latest.json"
    },
    {
      "from": "source:ghl",
      "relation": "contains",
      "to": "file:inputs/ghl/GHLCustomValues__JH4o9LqPhHyuvvyVFJVZ__Latest.json"
    },
    {
      "from": "source:ghl",
      "relation": "contains",
      "to": "file:inputs/ghl/GHLEmailTemplates__JH4o9LqPhHyuvvyVFJVZ__Latest.json"
    },
    {
      "from": "source:ghl",
      "relation": "contains",
      "to": "file:inputs/ghl/GHLForms__JH4o9LqPhHyuvvyVFJVZ__Latest.json"
    },
    {
      "from": "source:ghl",
      "relation": "contains",
      "to": "file:inputs/ghl/GHLFunnels__JH4o9LqPhHyuvvyVFJVZ__Latest.json"
    },
    {
      "from": "source:ghl",
      "relation": "contains",
      "to": "file:inputs/ghl/GHLLocation__JH4o9LqPhHyuvvyVFJVZ__Latest.json"
    },
    {
      "from": "source:ghl",
      "relation": "contains",
      "to": "file:inputs/ghl/GHLPipelines__JH4o9LqPhHyuvvyVFJVZ__Latest.json"
    },
    {
      "from": "source:ghl",
      "relation": "contains",
      "to": "file:inputs/ghl/GHLTags__JH4o9LqPhHyuvvyVFJVZ__Latest.json"
    },
    {
      "from": "source:ghl",
      "relation": "contains",
      "to": "file:inputs/ghl/GHLTriggerLinks__JH4o9LqPhHyuvvyVFJVZ__Latest.json"
    },
    {
      "from": "source:ghl",
      "relation": "contains",
      "to": "file:inputs/ghl/GHLUsers__JH4o9LqPhHyuvvyVFJVZ__Latest.json"
    },
    {
      "from": "source:ghl",
      "relation": "contains",
      "to": "file:inputs/ghl/GHLWorkflow__82cb0414-c64a-4fdd-8961-96719dea3878__Latest.json"
    },
    {
      "from": "source:ghl",
      "relation": "contains",
      "to": "file:inputs/ghl/GHLWorkflow__90cecd4e-e701-46bb-87c5-9aa43c2b0ea5__Latest.json"
    },
    {
      "from": "source:ghl",
      "relation": "contains",
      "to": "file:inputs/ghl/GHLWorkflows__JH4o9LqPhHyuvvyVFJVZ__Latest.json"
    },
    {
      "from": "source:ghl",
      "relation": "contains",
      "to": "file:inputs/ghl/README.md"
    },
    {
      "from": "source:make",
      "relation": "contains",
      "to": "file:inputs/make/MAKE_SCENARIOS.json"
    },
    {
      "from": "source:make",
      "relation": "contains",
      "to": "file:inputs/make/MAKE_SCENARIO_INDEX__Latest.json"
    },
    {
      "from": "source:make",
      "relation": "contains",
      "to": "file:inputs/make/MAKE_SCENARIO_LISTING__Latest.json"
    },
    {
      "from": "source:make",
      "relation": "contains",
      "to": "file:inputs/make/MakeProbe__Latest.json"
    },
    {
      "from": "source:make",
      "relation": "contains",
      "to": "file:inputs/make/README.md"
    },
    {
      "from": "source:make",
      "relation": "contains",
      "to": "file:inputs/make/blueprints/MakeBlueprint__2348337__Latest.json"
    },
    {
      "from": "source:make",
      "relation": "contains",
      "to": "file:inputs/make/blueprints/MakeBlueprint__3664392__Latest.json"
    },
    {
      "from": "source:make",
      "relation": "contains",
      "to": "file:inputs/make/blueprints/MakeBlueprint__3673026__Latest.json"
    },
    {
      "from": "source:make",
      "relation": "contains",
      "to": "file:inputs/make/blueprints/MakeBlueprint__3686763__Latest.json"
    },
    {
      "from": "source:make",
      "relation": "contains",
      "to": "file:inputs/make/blueprints/MakeBlueprint__3686991__Latest.json"
    },
    {
      "from": "source:make",
      "relation": "contains",
      "to": "file:inputs/make/blueprints/MakeBlueprint__3687011__Latest.json"
    },
    {
      "from": "source:make",
      "relation": "contains",
      "to": "file:inputs/make/blueprints/MakeBlueprint__3733465__Latest.json"
    },
    {
      "from": "source:make",
      "relation": "contains",
      "to": "file:inputs/make/blueprints/MakeBlueprint__3738189__Latest.json"
    },
    {
      "from": "source:make",
      "relation": "contains",
      "to": "file:inputs/make/blueprints/MakeBlueprint__3744510__Latest.json"
    },
    {
      "from": "source:make",
      "relation": "contains",
      "to": "file:inputs/make/blueprints/MakeBlueprint__3745933__Latest.json"
    },
    {
      "from": "source:make",
      "relation": "contains",
      "to": "file:inputs/make/blueprints/MakeBlueprint__3761572__Latest.json"
    },
    {
      "from": "source:make",
      "relation": "contains",
      "to": "file:inputs/make/blueprints/MakeBlueprint__3795815__Latest.json"
    },
    {
      "from": "source:make",
      "relation": "contains",
      "to": "file:inputs/make/blueprints/MakeBlueprint__3798600__Latest.json"
    },
    {
      "from": "source:make",
      "relation": "contains",
      "to": "file:inputs/make/blueprints/MakeBlueprint__3818644__Latest.json"
    },
    {
      "from": "source:make",
      "relation": "contains",
      "to": "file:inputs/make/blueprints/MakeBlueprint__3818650__Latest.json"
    },
    {
      "from": "source:make",
      "relation": "contains",
      "to": "file:inputs/make/blueprints/MakeBlueprint__3818652__Latest.json"
    },
    {
      "from": "source:make",
      "relation": "contains",
      "to": "file:inputs/make/blueprints/MakeBlueprint__3818663__Latest.json"
    },
    {
      "from": "source:make",
      "relation": "contains",
      "to": "file:inputs/make/blueprints/MakeBlueprint__3824254__Latest.json"
    },
    {
      "from": "source:make",
      "relation": "contains",
      "to": "file:inputs/make/blueprints/MakeBlueprint__3824833__Latest.json"
    },
    {
      "from": "source:make",
      "relation": "contains",
      "to": "file:inputs/make/blueprints/MakeBlueprint__3859876__Latest.json"
    },
    {
      "from": "source:make",
      "relation": "contains",
      "to": "file:inputs/make/blueprints/MakeBlueprint__3920516__Latest.json"
    },
    {
      "from": "source:make",
      "relation": "contains",
      "to": "file:inputs/make/blueprints/MakeBlueprint__3920818__Latest.json"
    },
    {
      "from": "source:make",
      "relation": "contains",
      "to": "file:inputs/make/blueprints/MakeBlueprint__3952284__Latest.json"
    },
    {
      "from": "source:make",
      "relation": "contains",
      "to": "file:inputs/make/blueprints/MakeBlueprint__3961170__Latest.json"
    },
    {
      "from": "source:make",
      "relation": "contains",
      "to": "file:inputs/make/blueprints/MakeBlueprint__3996198__Latest.json"
    },
    {
      "from": "source:make",
      "relation": "contains",
      "to": "file:inputs/make/blueprints/MakeBlueprint__4001823__Latest.json"
    },
    {
      "from": "source:make",
      "relation": "contains",
      "to": "file:inputs/make/blueprints/MakeBlueprint__4002164__Latest.json"
    },
    {
      "from": "source:make",
      "relation": "contains",
      "to": "file:inputs/make/blueprints/MakeBlueprint__4002272__Latest.json"
    },
    {
      "from": "source:make",
      "relation": "contains",
      "to": "file:inputs/make/blueprints/MakeBlueprint__4055279__Latest.json"
    },
    {
      "from": "source:make",
      "relation": "contains",
      "to": "file:inputs/make/blueprints/MakeBlueprint__4055283__Latest.json"
    },
    {
      "from": "source:make",
      "relation": "contains",
      "to": "file:inputs/make/blueprints/MakeBlueprint__4091455__Latest.json"
    },
    {
      "from": "source:make",
      "relation": "contains",
      "to": "file:inputs/make/blueprints/MakeBlueprint__4091456__Latest.json"
    },
    {
      "from": "source:make",
      "relation": "contains",
      "to": "file:inputs/make/blueprints/MakeBlueprint__4093385__Latest.json"
    },
    {
      "from": "source:make",
      "relation": "contains",
      "to": "file:inputs/make/blueprints/MakeBlueprint__4121916__Latest.json"
    },
    {
      "from": "source:make",
      "relation": "contains",
      "to": "file:inputs/make/blueprints/MakeBlueprint__4123962__Latest.json"
    },
    {
      "from": "source:make",
      "relation": "contains",
      "to": "file:inputs/make/blueprints/MakeBlueprint__4124710__Latest.json"
    },
    {
      "from": "source:make",
      "relation": "contains",
      "to": "file:inputs/make/blueprints/MakeBlueprint__4127837__Latest.json"
    },
    {
      "from": "source:make",
      "relation": "contains",
      "to": "file:inputs/make/blueprints/MakeBlueprint__4128249__Latest.json"
    },
    {
      "from": "source:make",
      "relation": "contains",
      "to": "file:inputs/make/blueprints/MakeBlueprint__4128593__Latest.json"
    },
    {
      "from": "source:make",
      "relation": "contains",
      "to": "file:inputs/make/blueprints/MakeBlueprint__4148204__Latest.json"
    },
    {
      "from": "source:make",
      "relation": "contains",
      "to": "file:inputs/make/blueprints/MakeBlueprint__4185478__Latest.json"
    },
    {
      "from": "source:make",
      "relation": "contains",
      "to": "file:inputs/make/blueprints/MakeBlueprint__4206316__Latest.json"
    },
    {
      "from": "source:make",
      "relation": "contains",
      "to": "file:inputs/make/blueprints/MakeBlueprint__4207345__Latest.json"
    },
    {
      "from": "source:make",
      "relation": "contains",
      "to": "file:inputs/make/blueprints/MakeBlueprint__4226576__Latest.json"
    },
    {
      "from": "source:make",
      "relation": "contains",
      "to": "file:inputs/make/blueprints/MakeBlueprint__4227392__Latest.json"
    },
    {
      "from": "source:make",
      "relation": "contains",
      "to": "file:inputs/make/blueprints/MakeBlueprint__4265554__Latest.json"
    },
    {
      "from": "source:make",
      "relation": "contains",
      "to": "file:inputs/make/blueprints/MakeBlueprint__4267051__Latest.json"
    },
    {
      "from": "source:make",
      "relation": "contains",
      "to": "file:inputs/make/blueprints/MakeBlueprint__4267120__Latest.json"
    },
    {
      "from": "source:make",
      "relation": "contains",
      "to": "file:inputs/make/blueprints/MakeBlueprint__4328562__Latest.json"
    },
    {
      "from": "source:make",
      "relation": "contains",
      "to": "file:inputs/make/blueprints/MakeBlueprint__4347798__Latest.json"
    },
    {
      "from": "source:make",
      "relation": "contains",
      "to": "file:inputs/make/blueprints/MakeBlueprint__4360004__Latest.json"
    },
    {
      "from": "source:make",
      "relation": "contains",
      "to": "file:inputs/make/blueprints/README.md"
    },
    {
      "from": "source:make",
      "relation": "contains",
      "to": "file:inputs/make/digests/MakeDigest__C12IntelReportDigest__3798600__v0.1.json.md"
    },
    {
      "from": "source:make",
      "relation": "contains",
      "to": "file:inputs/make/digests/MakeDigest__EmailConveyor__4093385__2026-02-12T15-09-37.json.md"
    },
    {
      "from": "source:make",
      "relation": "contains",
      "to": "file:inputs/make/digests/MakeDigest__IntelConveyor__4091455__v0.1.json.md"
    },
    {
      "from": "source:make",
      "relation": "contains",
      "to": "file:inputs/make/digests/README.md"
    },
    {
      "from": "source:models",
      "relation": "contains",
      "to": "file:inputs/models/system/index.md"
    },
    {
      "from": "source:qb",
      "relation": "contains",
      "to": "file:inputs/qb/QB Centurion Intel SEED (1).md"
    },
    {
      "from": "source:qb",
      "relation": "contains",
      "to": "file:inputs/qb/QB__CenturionIntel__v0.3.md"
    },
    {
      "from": "source:qb",
      "relation": "contains",
      "to": "file:inputs/qb/README.md"
    },
    {
      "from": "source:snapshots",
      "relation": "contains",
      "to": "file:inputs/snapshots/index.md"
    },
    {
      "from": "source:softr",
      "relation": "contains",
      "to": "file:inputs/softr/README.md"
    },
    {
      "from": "source:softr",
      "relation": "contains",
      "to": "file:inputs/softr/SoftrUsers__Latest.json"
    },
    {
      "from": "source:videoask",
      "relation": "contains",
      "to": "file:inputs/videoask/README.md"
    },
    {
      "from": "source:videoask",
      "relation": "contains",
      "to": "file:inputs/videoask/VideoAskForms__Latest.json"
    },
    {
      "from": "source:videopeel",
      "relation": "contains",
      "to": "file:inputs/videopeel/readme.md"
    },
    {
      "from": "source:web",
      "relation": "contains",
      "to": "file:inputs/web/readme.md"
    }
  ],
  "files": [
    {
      "extension": ".md",
      "json_top_level_keys": "UNKNOWN",
      "markdown_heading": "UNKNOWN",
      "path": "inputs/README.md",
      "sha256": "71f075203fe6ef1fe6d6c3bdeb265941ce42041c728f1d4b36e47b7cc13a509d",
      "size_bytes": 40,
      "source": "root"
    },
    {
      "extension": ".md",
      "json_top_level_keys": "UNKNOWN",
      "markdown_heading": "**Tables overview**",
      "path": "inputs/airtable/Airtable \u00b7 Dancing King Client Vault \u00b7 System Map \u00b7 v0.md",
      "sha256": "cae4d0e7503f662214d9444d7f6aafd4ce77449c0023f7486446a9b610c2d0e1",
      "size_bytes": 5710,
      "source": "airtable"
    },
    {
      "extension": ".docx",
      "json_top_level_keys": "UNKNOWN",
      "markdown_heading": "UNKNOWN",
      "path": "inputs/airtable/AirtableSchema__DancingKingClientVault__2026-02-12T14_19_55.058Z.json.docx",
      "sha256": "3d547e95d0116db1b6b7672ac3bcf71a55da025fc35ee518d5f480cff0205df3",
      "size_bytes": 45207,
      "source": "airtable"
    },
    {
      "extension": ".json",
      "json_top_level_keys": [
        "tables"
      ],
      "markdown_heading": "UNKNOWN",
      "path": "inputs/airtable/AirtableSchema__DancingKingClientVault__Latest.json",
      "sha256": "9913dd751b063d4e6c3cc3f34867d9d86a7f6d32059319d3d16bfefdd0df5598",
      "size_bytes": 173230,
      "source": "airtable"
    },
    {
      "extension": ".json",
      "json_top_level_keys": [
        "base_id",
        "fetched_at",
        "ok",
        "tables"
      ],
      "markdown_heading": "UNKNOWN",
      "path": "inputs/airtable/AirtableSchema__app0ezVqvqQRWTXIJ__Latest.json",
      "sha256": "e1db54b5be4c14c8adba06a340b839d362e48262d0d76f9d4e19fa8cc9b9f43b",
      "size_bytes": 340628,
      "source": "airtable"
    },
    {
      "extension": ".json",
      "json_top_level_keys": [
        "base_id",
        "fetched_at",
        "ok",
        "tables"
      ],
      "markdown_heading": "UNKNOWN",
      "path": "inputs/airtable/AirtableSchema__appQFyu6Aejoq7yHP__Latest.json",
      "sha256": "8ec870d07b8302ea7c33133a022c8e6a50feca60f282b4707ae16effbf7eb2b7",
      "size_bytes": 7948,
      "source": "airtable"
    },
    {
      "extension": ".md",
      "json_top_level_keys": "UNKNOWN",
      "markdown_heading": "Airtable inputs",
      "path": "inputs/airtable/README.md",
      "sha256": "0d1de866a40c94adb94b6be6fe295f5f5aa78a291d51fadd8bd2e07b3a9b3090",
      "size_bytes": 320,
      "source": "airtable"
    },
    {
      "extension": ".md",
      "json_top_level_keys": "UNKNOWN",
      "markdown_heading": "Change Notes Index",
      "path": "inputs/changelog/index.md",
      "sha256": "517a5cdc1054225ba6b998291ce36ac9f712a182f2a33928902df91ee6d7c114",
      "size_bytes": 525,
      "source": "changelog"
    },
    {
      "extension": ".md",
      "json_top_level_keys": "UNKNOWN",
      "markdown_heading": "UNKNOWN",
      "path": "inputs/clay/README.md",
      "sha256": "e1412f34f8f980eab6d1033f9a55a215203a51977b62de2158a083fe7d09eafe",
      "size_bytes": 91,
      "source": "clay"
    },
    {
      "extension": ".json",
      "json_top_level_keys": [
        "calendars",
        "count",
        "fetched_at",
        "location_id",
        "ok",
        "source",
        "status"
      ],
      "markdown_heading": "UNKNOWN",
      "path": "inputs/ghl/GHLCalendars__JH4o9LqPhHyuvvyVFJVZ__Latest.json",
      "sha256": "337f9dc716da4586776c5d7ed17d1630489b18596d31b45cfa3da3a3ac6bf90c",
      "size_bytes": 77023,
      "source": "ghl"
    },
    {
      "extension": ".json",
      "json_top_level_keys": [
        "contacts",
        "count",
        "fetched_at",
        "location_id",
        "ok",
        "source",
        "status"
      ],
      "markdown_heading": "UNKNOWN",
      "path": "inputs/ghl/GHLContacts__JH4o9LqPhHyuvvyVFJVZ__Latest.json",
      "sha256": "2fbe4a73a1ed8464452d7adb81d8f254dcacd6b76da904b2df85e39a0e5fc2f0",
      "size_bytes": 3870974,
      "source": "ghl"
    },
    {
      "extension": ".json",
      "json_top_level_keys": [
        "conversations",
        "count",
        "fetched_at",
        "location_id",
        "ok",
        "source",
        "status"
      ],
      "markdown_heading": "UNKNOWN",
      "path": "inputs/ghl/GHLConversations__JH4o9LqPhHyuvvyVFJVZ__Latest.json",
      "sha256": "811e8a40641c7988f31f50c39a69b3262da8c18af4e730e7e05939d3e84101cb",
      "size_bytes": 48435,
      "source": "ghl"
    },
    {
      "extension": ".json",
      "json_top_level_keys": [
        "count",
        "custom_fields",
        "fetched_at",
        "location_id",
        "ok",
        "source",
        "status"
      ],
      "markdown_heading": "UNKNOWN",
      "path": "inputs/ghl/GHLCustomFields__JH4o9LqPhHyuvvyVFJVZ__Latest.json",
      "sha256": "6ac89c932a1693b3e82a84696985b70ee35fcf84262f768b97c9543705ab1852",
      "size_bytes": 51456,
      "source": "ghl"
    },
    {
      "extension": ".json",
      "json_top_level_keys": [
        "count",
        "custom_values",
        "fetched_at",
        "location_id",
        "ok",
        "source",
        "status"
      ],
      "markdown_heading": "UNKNOWN",
      "path": "inputs/ghl/GHLCustomValues__JH4o9LqPhHyuvvyVFJVZ__Latest.json",
      "sha256": "2449862ca818411aa0d33a1b61c1784b9e214bf85807a09b616e34c87bc60d64",
      "size_bytes": 3911,
      "source": "ghl"
    },
    {
      "extension": ".json",
      "json_top_level_keys": [
        "count",
        "email_templates",
        "fetched_at",
        "location_id",
        "ok",
        "source",
        "status"
      ],
      "markdown_heading": "UNKNOWN",
      "path": "inputs/ghl/GHLEmailTemplates__JH4o9LqPhHyuvvyVFJVZ__Latest.json",
      "sha256": "660daf4c1c49e498ad0d12f8d8c937ee706050250f11157cecb04b61deca2044",
      "size_bytes": 172,
      "source": "ghl"
    },
    {
      "extension": ".json",
      "json_top_level_keys": [
        "count",
        "fetched_at",
        "forms",
        "location_id",
        "ok",
        "source",
        "status"
      ],
      "markdown_heading": "UNKNOWN",
      "path": "inputs/ghl/GHLForms__JH4o9LqPhHyuvvyVFJVZ__Latest.json",
      "sha256": "c07466c74e6698fa1bee39f38071f30f7615b210eae0dcbb6e9179a63560b004",
      "size_bytes": 1371,
      "source": "ghl"
    },
    {
      "extension": ".json",
      "json_top_level_keys": [
        "count",
        "fetched_at",
        "funnels",
        "location_id",
        "ok",
        "source",
        "status"
      ],
      "markdown_heading": "UNKNOWN",
      "path": "inputs/ghl/GHLFunnels__JH4o9LqPhHyuvvyVFJVZ__Latest.json",
      "sha256": "021238bf4ad447ae004b1b637471886c88e40ea95d895bf0556bde803f54466e",
      "size_bytes": 38082,
      "source": "ghl"
    },
    {
      "extension": ".json",
      "json_top_level_keys": [
        "fetched_at",
        "location",
        "location_id",
        "ok",
        "source",
        "status"
      ],
      "markdown_heading": "UNKNOWN",
      "path": "inputs/ghl/GHLLocation__JH4o9LqPhHyuvvyVFJVZ__Latest.json",
      "sha256": "e747acb404f309080a013342e0c79a47dd3c179e11e394459736cf0ad8940a8f",
      "size_bytes": 3626,
      "source": "ghl"
    },
    {
      "extension": ".json",
      "json_top_level_keys": [
        "count",
        "fetched_at",
        "location_id",
        "ok",
        "pipelines",
        "source",
        "status"
      ],
      "markdown_heading": "UNKNOWN",
      "path": "inputs/ghl/GHLPipelines__JH4o9LqPhHyuvvyVFJVZ__Latest.json",
      "sha256": "7b6018ce91ab6c17f98ace60776afc0e2efd8b4bb7a14fb75dd2326591f90143",
      "size_bytes": 11456,
      "source": "ghl"
    },
    {
      "extension": ".json",
      "json_top_level_keys": [
        "count",
        "fetched_at",
        "location_id",
        "ok",
        "source",
        "status",
        "tags"
      ],
      "markdown_heading": "UNKNOWN",
      "path": "inputs/ghl/GHLTags__JH4o9LqPhHyuvvyVFJVZ__Latest.json",
      "sha256": "23b40f08b89fc82a522d842e4222c93c9c227cafb86f3ed6bb227ad66e3955b6",
      "size_bytes": 6357,
      "source": "ghl"
    },
    {
      "extension": ".json",
      "json_top_level_keys": [
        "error",
        "fetched_at",
        "location_id",
        "ok",
        "source",
        "status",
        "trigger_links"
      ],
      "markdown_heading": "UNKNOWN",
      "path": "inputs/ghl/GHLTriggerLinks__JH4o9LqPhHyuvvyVFJVZ__Latest.json",
      "sha256": "d8b0ae31f62eaab33c20104a6d6c5ea0b1e55a3c17380257cf90f07ab20470d9",
      "size_bytes": 411,
      "source": "ghl"
    },
    {
      "extension": ".json",
      "json_top_level_keys": [
        "count",
        "fetched_at",
        "location_id",
        "ok",
        "source",
        "status",
        "users"
      ],
      "markdown_heading": "UNKNOWN",
      "path": "inputs/ghl/GHLUsers__JH4o9LqPhHyuvvyVFJVZ__Latest.json",
      "sha256": "06733a3f91d0933d4038ddf48634b1a0d4ef84ae9a9ed6e20387b343629fd5e5",
      "size_bytes": 11330,
      "source": "ghl"
    },
    {
      "extension": ".json",
      "json_top_level_keys": [
        "error",
        "fetched_at",
        "ok",
        "source",
        "status",
        "workflow",
        "workflow_id"
      ],
      "markdown_heading": "UNKNOWN",
      "path": "inputs/ghl/GHLWorkflow__82cb0414-c64a-4fdd-8961-96719dea3878__Latest.json",
      "sha256": "61fea5dd443458cf045cd141fe76913ce87f3c774ed0fba9fe7ec2fe8274f818",
      "size_bytes": 465,
      "source": "ghl"
    },
    {
      "extension": ".json",
      "json_top_level_keys": [
        "error",
        "fetched_at",
        "ok",
        "source",
        "status",
        "workflow",
        "workflow_id"
      ],
      "markdown_heading": "UNKNOWN",
      "path": "inputs/ghl/GHLWorkflow__90cecd4e-e701-46bb-87c5-9aa43c2b0ea5__Latest.json",
      "sha256": "53f0a657eb8d9289cc34b15122d93b8d5449f7fb3ae54a893d4cc688f469b57b",
      "size_bytes": 465,
      "source": "ghl"
    },
    {
      "extension": ".json",
      "json_top_level_keys": [
        "count",
        "fetched_at",
        "location_id",
        "ok",
        "source",
        "status",
        "workflows"
      ],
      "markdown_heading": "UNKNOWN",
      "path": "inputs/ghl/GHLWorkflows__JH4o9LqPhHyuvvyVFJVZ__Latest.json",
      "sha256": "03b3ebb9a0414825a8591596315fa412462f04a272810584e1d5f728d56c6873",
      "size_bytes": 11625,
      "source": "ghl"
    },
    {
      "extension": ".md",
      "json_top_level_keys": "UNKNOWN",
      "markdown_heading": "GHL inputs",
      "path": "inputs/ghl/README.md",
      "sha256": "fc4648180e38122827eb213adabc06bf4eb5bf1eec82358c10088e4ffcf75d4e",
      "size_bytes": 2749,
      "source": "ghl"
    },
    {
      "extension": ".json",
      "json_top_level_keys": [
        "scenario_ids"
      ],
      "markdown_heading": "UNKNOWN",
      "path": "inputs/make/MAKE_SCENARIOS.json",
      "sha256": "9ff94a0d4a7cf7e3c350b91993842be6a41e3dcfc3d0e7ac2e2b19930d2c73e5",
      "size_bytes": 162,
      "source": "make"
    },
    {
      "extension": ".json",
      "json_top_level_keys": [
        "base_url",
        "count",
        "fetched_at",
        "organization_id",
        "scenario_source",
        "scenarios",
        "team_id"
      ],
      "markdown_heading": "UNKNOWN",
      "path": "inputs/make/MAKE_SCENARIO_INDEX__Latest.json",
      "sha256": "453c156ded45f0f59637897c4e823aed0f01e52a35861d4523b1c2c5aff25235",
      "size_bytes": 5508,
      "source": "make"
    },
    {
      "extension": ".json",
      "json_top_level_keys": [
        "fetched_at",
        "ok",
        "organization_id",
        "raw",
        "scenarios",
        "status",
        "team_id"
      ],
      "markdown_heading": "UNKNOWN",
      "path": "inputs/make/MAKE_SCENARIO_LISTING__Latest.json",
      "sha256": "22900b68cc4ee539aff07ebd2feae754fb02c246a7918fe702b76bf3872dacc1",
      "size_bytes": 75941,
      "source": "make"
    },
    {
      "extension": ".json",
      "json_top_level_keys": [
        "base_url",
        "count",
        "fetched_at",
        "organization_id",
        "scenario_source",
        "scenarios",
        "team_id"
      ],
      "markdown_heading": "UNKNOWN",
      "path": "inputs/make/MakeProbe__Latest.json",
      "sha256": "2d79d3b33febfa19a98e65ef8dcda114afbc48770aae7d1d4a7310f20ad6ef10",
      "size_bytes": 6831,
      "source": "make"
    },
    {
      "extension": ".md",
      "json_top_level_keys": "UNKNOWN",
      "markdown_heading": "Make inputs",
      "path": "inputs/make/README.md",
      "sha256": "bd15888f70af735fc7f74527db150d07b210fef7bdfeb9870eb21cf7c3675169",
      "size_bytes": 575,
      "source": "make"
    },
    {
      "extension": ".json",
      "json_top_level_keys": [
        "fetched_at",
        "response",
        "scenario_id",
        "status"
      ],
      "markdown_heading": "UNKNOWN",
      "path": "inputs/make/blueprints/MakeBlueprint__2348337__Latest.json",
      "sha256": "db0563e3e3e1d505fb55d340c0b8bdc5b61cc54419d30c9d1c4acd9f993e2b66",
      "size_bytes": 29039,
      "source": "make"
    },
    {
      "extension": ".json",
      "json_top_level_keys": [
        "fetched_at",
        "response",
        "scenario_id",
        "status"
      ],
      "markdown_heading": "UNKNOWN",
      "path": "inputs/make/blueprints/MakeBlueprint__3664392__Latest.json",
      "sha256": "976aa052b3b4a97c902107b491548e160b1ace46a06abe57d6679363070e8bd1",
      "size_bytes": 133837,
      "source": "make"
    },
    {
      "extension": ".json",
      "json_top_level_keys": [
        "fetched_at",
        "response",
        "scenario_id",
        "status"
      ],
      "markdown_heading": "UNKNOWN",
      "path": "inputs/make/blueprints/MakeBlueprint__3673026__Latest.json",
      "sha256": "20a9b130cffb08d27eda231114106d11b09f752e1421dee9abd41750e7cfe9a9",
      "size_bytes": 193486,
      "source": "make"
    },
    {
      "extension": ".json",
      "json_top_level_keys": [
        "fetched_at",
        "response",
        "scenario_id",
        "status"
      ],
      "markdown_heading": "UNKNOWN",
      "path": "inputs/make/blueprints/MakeBlueprint__3686763__Latest.json",
      "sha256": "a5fd21c8659e313f86c0957ba8e8926c445fd1581c1713e679e505a4640e3ab7",
      "size_bytes": 132491,
      "source": "make"
    },
    {
      "extension": ".json",
      "json_top_level_keys": [
        "fetched_at",
        "response",
        "scenario_id",
        "status"
      ],
      "markdown_heading": "UNKNOWN",
      "path": "inputs/make/blueprints/MakeBlueprint__3686991__Latest.json",
      "sha256": "6c0ca22a6f15f6d01e796111f3d8dfed6629ad919a8b7bf9763eec94b8e9ef35",
      "size_bytes": 138096,
      "source": "make"
    },
    {
      "extension": ".json",
      "json_top_level_keys": [
        "fetched_at",
        "response",
        "scenario_id",
        "status"
      ],
      "markdown_heading": "UNKNOWN",
      "path": "inputs/make/blueprints/MakeBlueprint__3687011__Latest.json",
      "sha256": "527f01b2a62aa917e5384f364799fb6a5de041f84bc6f1c6ef28b754a9e60ea2",
      "size_bytes": 87666,
      "source": "make"
    },
    {
      "extension": ".json",
      "json_top_level_keys": [
        "fetched_at",
        "response",
        "scenario_id",
        "status"
      ],
      "markdown_heading": "UNKNOWN",
      "path": "inputs/make/blueprints/MakeBlueprint__3733465__Latest.json",
      "sha256": "55cb730c61fb138798102c6e2de0c226aa5fb2ea5fd014d46bcc912931af328e",
      "size_bytes": 571925,
      "source": "make"
    },
    {
      "extension": ".json",
      "json_top_level_keys": [
        "fetched_at",
        "response",
        "scenario_id",
        "status"
      ],
      "markdown_heading": "UNKNOWN",
      "path": "inputs/make/blueprints/MakeBlueprint__3738189__Latest.json",
      "sha256": "bdd9332e0000ebedc1f166f688976f8b959176639f1b7ea6290cc4bc64d2950e",
      "size_bytes": 146399,
      "source": "make"
    },
    {
      "extension": ".json",
      "json_top_level_keys": [
        "fetched_at",
        "response",
        "scenario_id",
        "status"
      ],
      "markdown_heading": "UNKNOWN",
      "path": "inputs/make/blueprints/MakeBlueprint__3744510__Latest.json",
      "sha256": "d67768be34f6b6a22f13648ca01e3c0bf507827187bd07aea3c223cf55bb39cb",
      "size_bytes": 338031,
      "source": "make"
    },
    {
      "extension": ".json",
      "json_top_level_keys": [
        "fetched_at",
        "response",
        "scenario_id",
        "status"
      ],
      "markdown_heading": "UNKNOWN",
      "path": "inputs/make/blueprints/MakeBlueprint__3745933__Latest.json",
      "sha256": "f5e582cc982ae633bd800fce88940bdc83752cbe955db1602208686aacbdae5c",
      "size_bytes": 124315,
      "source": "make"
    },
    {
      "extension": ".json",
      "json_top_level_keys": [
        "fetched_at",
        "response",
        "scenario_id",
        "status"
      ],
      "markdown_heading": "UNKNOWN",
      "path": "inputs/make/blueprints/MakeBlueprint__3761572__Latest.json",
      "sha256": "e0e3998dbdfe88958ddeb7387c641dd3f1af5a0a4f6d524b0529f2d437520ce5",
      "size_bytes": 230606,
      "source": "make"
    },
    {
      "extension": ".json",
      "json_top_level_keys": [
        "fetched_at",
        "response",
        "scenario_id",
        "status"
      ],
      "markdown_heading": "UNKNOWN",
      "path": "inputs/make/blueprints/MakeBlueprint__3795815__Latest.json",
      "sha256": "8088390ae37946fa584fab069a843eaa267f6fa9cc381fa50860f30ee6fa8a06",
      "size_bytes": 211984,
      "source": "make"
    },
    {
      "extension": ".json",
      "json_top_level_keys": [
        "fetched_at",
        "response",
        "scenario_id",
        "status"
      ],
      "markdown_heading": "UNKNOWN",
      "path": "inputs/make/blueprints/MakeBlueprint__3798600__Latest.json",
      "sha256": "84fc7beb9742f63ae0e24c584b48f2ab14b3dfaa98fa1514f9e66bdf758ddea7",
      "size_bytes": 300381,
      "source": "make"
    },
    {
      "extension": ".json",
      "json_top_level_keys": [
        "fetched_at",
        "response",
        "scenario_id",
        "status"
      ],
      "markdown_heading": "UNKNOWN",
      "path": "inputs/make/blueprints/MakeBlueprint__3818644__Latest.json",
      "sha256": "4a22760f45c644f3974174e916157dbf2b72a769bea6434406b6edf3cbdfdb77",
      "size_bytes": 195490,
      "source": "make"
    },
    {
      "extension": ".json",
      "json_top_level_keys": [
        "fetched_at",
        "response",
        "scenario_id",
        "status"
      ],
      "markdown_heading": "UNKNOWN",
      "path": "inputs/make/blueprints/MakeBlueprint__3818650__Latest.json",
      "sha256": "923910ab3e0387b283edb2bd4f0dc473ed3046420b61eadc90546fea53e854a3",
      "size_bytes": 188936,
      "source": "make"
    },
    {
      "extension": ".json",
      "json_top_level_keys": [
        "fetched_at",
        "response",
        "scenario_id",
        "status"
      ],
      "markdown_heading": "UNKNOWN",
      "path": "inputs/make/blueprints/MakeBlueprint__3818652__Latest.json",
      "sha256": "55e200ba6d0c1b8415c198cd3dc99e048e8ea3ed47b368b54e1194db9bacd61a",
      "size_bytes": 214238,
      "source": "make"
    },
    {
      "extension": ".json",
      "json_top_level_keys": [
        "fetched_at",
        "response",
        "scenario_id",
        "status"
      ],
      "markdown_heading": "UNKNOWN",
      "path": "inputs/make/blueprints/MakeBlueprint__3818663__Latest.json",
      "sha256": "6dda1fe0ab7b3b5e75c8aa18ed09a5c5a00f8a46ed2ab65b33973d42747d6f86",
      "size_bytes": 198409,
      "source": "make"
    },
    {
      "extension": ".json",
      "json_top_level_keys": [
        "fetched_at",
        "response",
        "scenario_id",
        "status"
      ],
      "markdown_heading": "UNKNOWN",
      "path": "inputs/make/blueprints/MakeBlueprint__3824254__Latest.json",
      "sha256": "fc55a6fa5a39e6f9edaf381ea570954249f86d55254578f9b659917e453da134",
      "size_bytes": 498670,
      "source": "make"
    },
    {
      "extension": ".json",
      "json_top_level_keys": [
        "fetched_at",
        "response",
        "scenario_id",
        "status"
      ],
      "markdown_heading": "UNKNOWN",
      "path": "inputs/make/blueprints/MakeBlueprint__3824833__Latest.json",
      "sha256": "1a93e108d32c2b2beacc63f16fa42d1e5a4c6398a7e4741a6c914d4923c3e8fe",
      "size_bytes": 214975,
      "source": "make"
    },
    {
      "extension": ".json",
      "json_top_level_keys": [
        "fetched_at",
        "response",
        "scenario_id",
        "status"
      ],
      "markdown_heading": "UNKNOWN",
      "path": "inputs/make/blueprints/MakeBlueprint__3859876__Latest.json",
      "sha256": "1cbc5c2bea031a02dd98579afc160a9737c04b03eecfb234063a2b25c38e14b2",
      "size_bytes": 3320532,
      "source": "make"
    },
    {
      "extension": ".json",
      "json_top_level_keys": [
        "fetched_at",
        "response",
        "scenario_id",
        "status"
      ],
      "markdown_heading": "UNKNOWN",
      "path": "inputs/make/blueprints/MakeBlueprint__3920516__Latest.json",
      "sha256": "291f15f5f1050ae2797fce41154ec7f2927f0a608bf9e79bf79ca34c0eb1e7b3",
      "size_bytes": 211170,
      "source": "make"
    },
    {
      "extension": ".json",
      "json_top_level_keys": [
        "fetched_at",
        "response",
        "scenario_id",
        "status"
      ],
      "markdown_heading": "UNKNOWN",
      "path": "inputs/make/blueprints/MakeBlueprint__3920818__Latest.json",
      "sha256": "d363dcae1e3c9358e6c84befb320549c539ec6713a19836ddde0e80ee985e2b9",
      "size_bytes": 226847,
      "source": "make"
    },
    {
      "extension": ".json",
      "json_top_level_keys": [
        "fetched_at",
        "response",
        "scenario_id",
        "status"
      ],
      "markdown_heading": "UNKNOWN",
      "path": "inputs/make/blueprints/MakeBlueprint__3952284__Latest.json",
      "sha256": "550c4ec32103edaa5541c66b7497c7db2437dd0d18607e264ae5b737fd6b31a9",
      "size_bytes": 298372,
      "source": "make"
    },
    {
      "extension": ".json",
      "json_top_level_keys": [
        "fetched_at",
        "response",
        "scenario_id",
        "status"
      ],
      "markdown_heading": "UNKNOWN",
      "path": "inputs/make/blueprints/MakeBlueprint__3961170__Latest.json",
      "sha256": "bd250a6f4d2d2d7391ec2110c0769119bad59ad795e82da978a3f9613f986b0e",
      "size_bytes": 571916,
      "source": "make"
    },
    {
      "extension": ".json",
      "json_top_level_keys": [
        "fetched_at",
        "response",
        "scenario_id",
        "status"
      ],
      "markdown_heading": "UNKNOWN",
      "path": "inputs/make/blueprints/MakeBlueprint__3996198__Latest.json",
      "sha256": "297e6f03942e3baca6b6441d4b15d0c8adf17742855bd10dba03aa311f6e5178",
      "size_bytes": 25316,
      "source": "make"
    },
    {
      "extension": ".json",
      "json_top_level_keys": [
        "fetched_at",
        "response",
        "scenario_id",
        "status"
      ],
      "markdown_heading": "UNKNOWN",
      "path": "inputs/make/blueprints/MakeBlueprint__4001823__Latest.json",
      "sha256": "8d6dae8a173d2b55574dd6e3c2751d3f33a60c14e0e245107b3d0fb7a8d644a1",
      "size_bytes": 39815,
      "source": "make"
    },
    {
      "extension": ".json",
      "json_top_level_keys": [
        "fetched_at",
        "response",
        "scenario_id",
        "status"
      ],
      "markdown_heading": "UNKNOWN",
      "path": "inputs/make/blueprints/MakeBlueprint__4002164__Latest.json",
      "sha256": "e132020e450cbbb7998e2c0b560343cbec5966aecd7db47ef892860090e8682e",
      "size_bytes": 32336,
      "source": "make"
    },
    {
      "extension": ".json",
      "json_top_level_keys": [
        "fetched_at",
        "response",
        "scenario_id",
        "status"
      ],
      "markdown_heading": "UNKNOWN",
      "path": "inputs/make/blueprints/MakeBlueprint__4002272__Latest.json",
      "sha256": "97859481fbdaa51d31a65c9e8cbe7f05cc9f1d4de332c9177f79596a137f2b5c",
      "size_bytes": 28557,
      "source": "make"
    },
    {
      "extension": ".json",
      "json_top_level_keys": [
        "fetched_at",
        "response",
        "scenario_id",
        "status"
      ],
      "markdown_heading": "UNKNOWN",
      "path": "inputs/make/blueprints/MakeBlueprint__4055279__Latest.json",
      "sha256": "7c3d061e034f69846ea9a480f8dd48fa4c6a2d33091ce03b71f8cb34e09dfe36",
      "size_bytes": 226864,
      "source": "make"
    },
    {
      "extension": ".json",
      "json_top_level_keys": [
        "fetched_at",
        "response",
        "scenario_id",
        "status"
      ],
      "markdown_heading": "UNKNOWN",
      "path": "inputs/make/blueprints/MakeBlueprint__4055283__Latest.json",
      "sha256": "20cd5965097e6938afff9548a55b44ac8e3abcd3583125a06dcac08cbca558d5",
      "size_bytes": 221165,
      "source": "make"
    },
    {
      "extension": ".json",
      "json_top_level_keys": [
        "fetched_at",
        "response",
        "scenario_id",
        "status"
      ],
      "markdown_heading": "UNKNOWN",
      "path": "inputs/make/blueprints/MakeBlueprint__4091455__Latest.json",
      "sha256": "82cf828e8cb396c602112c03c7fc1941066e034f1f24a3438f4b1ae6e96a8925",
      "size_bytes": 998939,
      "source": "make"
    },
    {
      "extension": ".json",
      "json_top_level_keys": [
        "fetched_at",
        "response",
        "scenario_id",
        "status"
      ],
      "markdown_heading": "UNKNOWN",
      "path": "inputs/make/blueprints/MakeBlueprint__4091456__Latest.json",
      "sha256": "eaa2b9f4cda8f883fae52069b9cd90c80727ee7889e1d9f014ec86916b59ff60",
      "size_bytes": 211991,
      "source": "make"
    },
    {
      "extension": ".json",
      "json_top_level_keys": [
        "fetched_at",
        "response",
        "scenario_id",
        "status"
      ],
      "markdown_heading": "UNKNOWN",
      "path": "inputs/make/blueprints/MakeBlueprint__4093385__Latest.json",
      "sha256": "c8c0ad001b61b7555cb7d32a013a1ff148b6077f699338533a575fa4289e4b74",
      "size_bytes": 822256,
      "source": "make"
    },
    {
      "extension": ".json",
      "json_top_level_keys": [
        "fetched_at",
        "response",
        "scenario_id",
        "status"
      ],
      "markdown_heading": "UNKNOWN",
      "path": "inputs/make/blueprints/MakeBlueprint__4121916__Latest.json",
      "sha256": "2275e452ff93e5505a71fb124581e2dae15bdb0783665169ad3c722da6dc2cd3",
      "size_bytes": 25496,
      "source": "make"
    },
    {
      "extension": ".json",
      "json_top_level_keys": [
        "fetched_at",
        "response",
        "scenario_id",
        "status"
      ],
      "markdown_heading": "UNKNOWN",
      "path": "inputs/make/blueprints/MakeBlueprint__4123962__Latest.json",
      "sha256": "1c1f06941c88b9b692dd155f684fda238adacc9441bc93a5cafa615558cd8465",
      "size_bytes": 20567,
      "source": "make"
    },
    {
      "extension": ".json",
      "json_top_level_keys": [
        "fetched_at",
        "response",
        "scenario_id",
        "status"
      ],
      "markdown_heading": "UNKNOWN",
      "path": "inputs/make/blueprints/MakeBlueprint__4124710__Latest.json",
      "sha256": "6293bb9398dffbfdcd75a93a6e5f89b5042ac89fd21cda36564a56f7ef9a66ce",
      "size_bytes": 23818,
      "source": "make"
    },
    {
      "extension": ".json",
      "json_top_level_keys": [
        "fetched_at",
        "response",
        "scenario_id",
        "status"
      ],
      "markdown_heading": "UNKNOWN",
      "path": "inputs/make/blueprints/MakeBlueprint__4127837__Latest.json",
      "sha256": "4fe21fd1d8c6a4f9c91a17c19023f5cb3c4244f77cbd65212a0aacef4e472925",
      "size_bytes": 17022,
      "source": "make"
    },
    {
      "extension": ".json",
      "json_top_level_keys": [
        "fetched_at",
        "response",
        "scenario_id",
        "status"
      ],
      "markdown_heading": "UNKNOWN",
      "path": "inputs/make/blueprints/MakeBlueprint__4128249__Latest.json",
      "sha256": "05409442772aceb4a7c840ce3037aa35bf3aa105ff60f2df4a1b0d830624fcb8",
      "size_bytes": 16293,
      "source": "make"
    },
    {
      "extension": ".json",
      "json_top_level_keys": [
        "fetched_at",
        "response",
        "scenario_id",
        "status"
      ],
      "markdown_heading": "UNKNOWN",
      "path": "inputs/make/blueprints/MakeBlueprint__4128593__Latest.json",
      "sha256": "ab3806014a7339cfe055e57821795461443796d9400be1ecbf5e5f8caf4e68c8",
      "size_bytes": 12783,
      "source": "make"
    },
    {
      "extension": ".json",
      "json_top_level_keys": [
        "fetched_at",
        "response",
        "scenario_id",
        "status"
      ],
      "markdown_heading": "UNKNOWN",
      "path": "inputs/make/blueprints/MakeBlueprint__4148204__Latest.json",
      "sha256": "96dd0065d1f9c306b645c15cbfd53d4b4b5d8cfb045a6d42e45439947f65004e",
      "size_bytes": 217379,
      "source": "make"
    },
    {
      "extension": ".json",
      "json_top_level_keys": [
        "fetched_at",
        "response",
        "scenario_id",
        "status"
      ],
      "markdown_heading": "UNKNOWN",
      "path": "inputs/make/blueprints/MakeBlueprint__4185478__Latest.json",
      "sha256": "16199b8b5bd140bd2ce1cc4b63ab1ccd4ad1a2eb49299c4152e420732c4e92da",
      "size_bytes": 1436544,
      "source": "make"
    },
    {
      "extension": ".json",
      "json_top_level_keys": [
        "fetched_at",
        "response",
        "scenario_id",
        "status"
      ],
      "markdown_heading": "UNKNOWN",
      "path": "inputs/make/blueprints/MakeBlueprint__4206316__Latest.json",
      "sha256": "8d392f316ad7d5d412919785683c38623a3707ce20e90c17180853df6fe3d2c4",
      "size_bytes": 26384,
      "source": "make"
    },
    {
      "extension": ".json",
      "json_top_level_keys": [
        "fetched_at",
        "response",
        "scenario_id",
        "status"
      ],
      "markdown_heading": "UNKNOWN",
      "path": "inputs/make/blueprints/MakeBlueprint__4207345__Latest.json",
      "sha256": "8fab3303eabdb4f7b627703dd76b1a5d7570efff2270bc068fd12ac214efb33b",
      "size_bytes": 12419,
      "source": "make"
    },
    {
      "extension": ".json",
      "json_top_level_keys": [
        "fetched_at",
        "response",
        "scenario_id",
        "status"
      ],
      "markdown_heading": "UNKNOWN",
      "path": "inputs/make/blueprints/MakeBlueprint__4226576__Latest.json",
      "sha256": "e2273e351378ff807b96d954c5995d095398cc9409ad8eeb79335a862d8df3f3",
      "size_bytes": 164075,
      "source": "make"
    },
    {
      "extension": ".json",
      "json_top_level_keys": [
        "fetched_at",
        "response",
        "scenario_id",
        "status"
      ],
      "markdown_heading": "UNKNOWN",
      "path": "inputs/make/blueprints/MakeBlueprint__4227392__Latest.json",
      "sha256": "d35d025899b7c8c9fd6af6866027ddc802492cd41215b4f9e475253d622de9ea",
      "size_bytes": 97502,
      "source": "make"
    },
    {
      "extension": ".json",
      "json_top_level_keys": [
        "fetched_at",
        "response",
        "scenario_id",
        "status"
      ],
      "markdown_heading": "UNKNOWN",
      "path": "inputs/make/blueprints/MakeBlueprint__4265554__Latest.json",
      "sha256": "901226afa56a10ba554c895ca1e89e9cd032b5950e1e35e07c307f61c31cfe2f",
      "size_bytes": 714798,
      "source": "make"
    },
    {
      "extension": ".json",
      "json_top_level_keys": [
        "fetched_at",
        "response",
        "scenario_id",
        "status"
      ],
      "markdown_heading": "UNKNOWN",
      "path": "inputs/make/blueprints/MakeBlueprint__4267051__Latest.json",
      "sha256": "616c77ead0c5ec9c8930b7fb21914eca3e23c8f068401af816700b290f454d25",
      "size_bytes": 964274,
      "source": "make"
    },
    {
      "extension": ".json",
      "json_top_level_keys": [
        "fetched_at",
        "response",
        "scenario_id",
        "status"
      ],
      "markdown_heading": "UNKNOWN",
      "path": "inputs/make/blueprints/MakeBlueprint__4267120__Latest.json",
      "sha256": "1ac4ca9fc2eeb721dfadba00fd15e5c7a40d078c6d8a4c167a6355d91276d935",
      "size_bytes": 82247,
      "source": "make"
    },
    {
      "extension": ".json",
      "json_top_level_keys": [
        "fetched_at",
        "response",
        "scenario_id",
        "status"
      ],
      "markdown_heading": "UNKNOWN",
      "path": "inputs/make/blueprints/MakeBlueprint__4328562__Latest.json",
      "sha256": "dbe812ddfe0d12065a52c0a42969aaf25a738fdb16b7b836898517e2a3e057fb",
      "size_bytes": 16101,
      "source": "make"
    },
    {
      "extension": ".json",
      "json_top_level_keys": [
        "fetched_at",
        "response",
        "scenario_id",
        "status"
      ],
      "markdown_heading": "UNKNOWN",
      "path": "inputs/make/blueprints/MakeBlueprint__4347798__Latest.json",
      "sha256": "434b34e0ded55da3ae10598ccd9d49e1c4d6c5d00e4c878134afab200ce45ec8",
      "size_bytes": 1029901,
      "source": "make"
    },
    {
      "extension": ".json",
      "json_top_level_keys": [
        "fetched_at",
        "response",
        "scenario_id",
        "status"
      ],
      "markdown_heading": "UNKNOWN",
      "path": "inputs/make/blueprints/MakeBlueprint__4360004__Latest.json",
      "sha256": "284feb7a560a65e16c3f17f12c812b025c51038df72be9e83248bc8c3dc75a49",
      "size_bytes": 1046362,
      "source": "make"
    },
    {
      "extension": ".md",
      "json_top_level_keys": "UNKNOWN",
      "markdown_heading": "UNKNOWN",
      "path": "inputs/make/blueprints/README.md",
      "sha256": "01ba4719c80b6fe911b091a7c05124b64eeece964e09c058ef8f9805daca546b",
      "size_bytes": 1,
      "source": "make"
    },
    {
      "extension": ".md",
      "json_top_level_keys": "UNKNOWN",
      "markdown_heading": "**C12 Intel Report \u2013 Scenario Digest**",
      "path": "inputs/make/digests/MakeDigest__C12IntelReportDigest__3798600__v0.1.json.md",
      "sha256": "20d070c17715a79f76e8e70250313c5a84d7d093676800babe0330abe75d7248",
      "size_bytes": 10566,
      "source": "make"
    },
    {
      "extension": ".md",
      "json_top_level_keys": "UNKNOWN",
      "markdown_heading": "**1\\. Scenario Overview**",
      "path": "inputs/make/digests/MakeDigest__EmailConveyor__4093385__2026-02-12T15-09-37.json.md",
      "sha256": "e90aa6df102bf254902c60ce550c539d26e2ac5cc475d43d61d9c0c821ac8803",
      "size_bytes": 12100,
      "source": "make"
    },
    {
      "extension": ".md",
      "json_top_level_keys": "UNKNOWN",
      "markdown_heading": "**1\\. Scenario Overview**",
      "path": "inputs/make/digests/MakeDigest__IntelConveyor__4091455__v0.1.json.md",
      "sha256": "53a77d65c43a715a2698931f84cba84658529ab52d75a399c758245b5d6c7d76",
      "size_bytes": 14971,
      "source": "make"
    },
    {
      "extension": ".md",
      "json_top_level_keys": "UNKNOWN",
      "markdown_heading": "UNKNOWN",
      "path": "inputs/make/digests/README.md",
      "sha256": "01ba4719c80b6fe911b091a7c05124b64eeece964e09c058ef8f9805daca546b",
      "size_bytes": 1,
      "source": "make"
    },
    {
      "extension": ".md",
      "json_top_level_keys": "UNKNOWN",
      "markdown_heading": "System Model Index",
      "path": "inputs/models/system/index.md",
      "sha256": "215a32cbe77d5ae84e6c7deac090b17d4895902a8cff6a4a0e26ff33b9ef6ab6",
      "size_bytes": 623,
      "source": "models"
    },
    {
      "extension": ".md",
      "json_top_level_keys": "UNKNOWN",
      "markdown_heading": "UNKNOWN",
      "path": "inputs/qb/QB Centurion Intel SEED (1).md",
      "sha256": "42562596853325b26e87daf7d81b090ca2523952fc75bc22c46ab6ee5b329917",
      "size_bytes": 12159,
      "source": "qb"
    },
    {
      "extension": ".md",
      "json_top_level_keys": "UNKNOWN",
      "markdown_heading": "**QB\\_\\_CenturionIntel\\_\\_v0.3**",
      "path": "inputs/qb/QB__CenturionIntel__v0.3.md",
      "sha256": "4d3e18a9432cf30e6f5cdda7cb91e8caa52dcc7533f54dce62010d871eb5023e",
      "size_bytes": 29010,
      "source": "qb"
    },
    {
      "extension": ".md",
      "json_top_level_keys": "UNKNOWN",
      "markdown_heading": "UNKNOWN",
      "path": "inputs/qb/README.md",
      "sha256": "01ba4719c80b6fe911b091a7c05124b64eeece964e09c058ef8f9805daca546b",
      "size_bytes": 1,
      "source": "qb"
    },
    {
      "extension": ".md",
      "json_top_level_keys": "UNKNOWN",
      "markdown_heading": "Snapshot Index",
      "path": "inputs/snapshots/index.md",
      "sha256": "bcdc19bcd1f39d6fb372d519e0f8b31ae845dfa9ddee87aae7fa15862801b21c",
      "size_bytes": 783,
      "source": "snapshots"
    },
    {
      "extension": ".md",
      "json_top_level_keys": "UNKNOWN",
      "markdown_heading": "Softr inputs",
      "path": "inputs/softr/README.md",
      "sha256": "2ec04e8d4f3221fb2b967f16e33bbd543e09552a9199d00b6c9237320844a4b4",
      "size_bytes": 371,
      "source": "softr"
    },
    {
      "extension": ".json",
      "json_top_level_keys": [
        "count",
        "fetched_at",
        "ok",
        "source",
        "status",
        "users"
      ],
      "markdown_heading": "UNKNOWN",
      "path": "inputs/softr/SoftrUsers__Latest.json",
      "sha256": "7f496e0da12e7032d34c40b9ceb0d2988ff88205645669ffe9ae9ffade3baff1",
      "size_bytes": 123,
      "source": "softr"
    },
    {
      "extension": ".md",
      "json_top_level_keys": "UNKNOWN",
      "markdown_heading": "VideoAsk inputs",
      "path": "inputs/videoask/README.md",
      "sha256": "58ed9d7c5deb084021349511eed0b933614ad32a7767ae3a5883691354a49e11",
      "size_bytes": 418,
      "source": "videoask"
    },
    {
      "extension": ".json",
      "json_top_level_keys": [
        "count",
        "fetched_at",
        "forms",
        "ok",
        "source",
        "status"
      ],
      "markdown_heading": "UNKNOWN",
      "path": "inputs/videoask/VideoAskForms__Latest.json",
      "sha256": "7d5bd68ecdec501879cc7addc30b8bf19e1d56be1e727d32969e8acf716a3d1f",
      "size_bytes": 55381,
      "source": "videoask"
    },
    {
      "extension": ".md",
      "json_top_level_keys": "UNKNOWN",
      "markdown_heading": "UNKNOWN",
      "path": "inputs/videopeel/readme.md",
      "sha256": "01ba4719c80b6fe911b091a7c05124b64eeece964e09c058ef8f9805daca546b",
      "size_bytes": 1,
      "source": "videopeel"
    },
    {
      "extension": ".md",
      "json_top_level_keys": "UNKNOWN",
      "markdown_heading": "UNKNOWN",
      "path": "inputs/web/readme.md",
      "sha256": "01ba4719c80b6fe911b091a7c05124b64eeece964e09c058ef8f9805daca546b",
      "size_bytes": 1,
      "source": "web"
    }
  ],
  "inferred_system_structure": "UNKNOWN",
  "inputs_root": "inputs",
  "nodes": [
    {
      "id": "atlas",
      "kind": "atlas",
      "label": "Centurion Intel Atlas"
    },
    {
      "id": "source:airtable",
      "kind": "source",
      "label": "airtable"
    },
    {
      "id": "source:changelog",
      "kind": "source",
      "label": "changelog"
    },
    {
      "id": "source:clay",
      "kind": "source",
      "label": "clay"
    },
    {
      "id": "source:ghl",
      "kind": "source",
      "label": "ghl"
    },
    {
      "id": "source:make",
      "kind": "source",
      "label": "make"
    },
    {
      "id": "source:models",
      "kind": "source",
      "label": "models"
    },
    {
      "id": "source:qb",
      "kind": "source",
      "label": "qb"
    },
    {
      "id": "source:root",
      "kind": "source",
      "label": "root"
    },
    {
      "id": "source:snapshots",
      "kind": "source",
      "label": "snapshots"
    },
    {
      "id": "source:softr",
      "kind": "source",
      "label": "softr"
    },
    {
      "id": "source:videoask",
      "kind": "source",
      "label": "videoask"
    },
    {
      "id": "source:videopeel",
      "kind": "source",
      "label": "videopeel"
    },
    {
      "id": "source:web",
      "kind": "source",
      "label": "web"
    },
    {
      "extension": ".md",
      "id": "file:inputs/README.md",
      "kind": "file",
      "label": "inputs/README.md",
      "source": "root"
    },
    {
      "extension": ".md",
      "id": "file:inputs/airtable/Airtable \u00b7 Dancing King Client Vault \u00b7 System Map \u00b7 v0.md",
      "kind": "file",
      "label": "inputs/airtable/Airtable \u00b7 Dancing King Client Vault \u00b7 System Map \u00b7 v0.md",
      "source": "airtable"
    },
    {
      "extension": ".docx",
      "id": "file:inputs/airtable/AirtableSchema__DancingKingClientVault__2026-02-12T14_19_55.058Z.json.docx",
      "kind": "file",
      "label": "inputs/airtable/AirtableSchema__DancingKingClientVault__2026-02-12T14_19_55.058Z.json.docx",
      "source": "airtable"
    },
    {
      "extension": ".json",
      "id": "file:inputs/airtable/AirtableSchema__DancingKingClientVault__Latest.json",
      "kind": "file",
      "label": "inputs/airtable/AirtableSchema__DancingKingClientVault__Latest.json",
      "source": "airtable"
    },
    {
      "extension": ".json",
      "id": "file:inputs/airtable/AirtableSchema__app0ezVqvqQRWTXIJ__Latest.json",
      "kind": "file",
      "label": "inputs/airtable/AirtableSchema__app0ezVqvqQRWTXIJ__Latest.json",
      "source": "airtable"
    },
    {
      "extension": ".json",
      "id": "file:inputs/airtable/AirtableSchema__appQFyu6Aejoq7yHP__Latest.json",
      "kind": "file",
      "label": "inputs/airtable/AirtableSchema__appQFyu6Aejoq7yHP__Latest.json",
      "source": "airtable"
    },
    {
      "extension": ".md",
      "id": "file:inputs/airtable/README.md",
      "kind": "file",
      "label": "inputs/airtable/README.md",
      "source": "airtable"
    },
    {
      "extension": ".md",
      "id": "file:inputs/changelog/index.md",
      "kind": "file",
      "label": "inputs/changelog/index.md",
      "source": "changelog"
    },
    {
      "extension": ".md",
      "id": "file:inputs/clay/README.md",
      "kind": "file",
      "label": "inputs/clay/README.md",
      "source": "clay"
    },
    {
      "extension": ".json",
      "id": "file:inputs/ghl/GHLCalendars__JH4o9LqPhHyuvvyVFJVZ__Latest.json",
      "kind": "file",
      "label": "inputs/ghl/GHLCalendars__JH4o9LqPhHyuvvyVFJVZ__Latest.json",
      "source": "ghl"
    },
    {
      "extension": ".json",
      "id": "file:inputs/ghl/GHLContacts__JH4o9LqPhHyuvvyVFJVZ__Latest.json",
      "kind": "file",
      "label": "inputs/ghl/GHLContacts__JH4o9LqPhHyuvvyVFJVZ__Latest.json",
      "source": "ghl"
    },
    {
      "extension": ".json",
      "id": "file:inputs/ghl/GHLConversations__JH4o9LqPhHyuvvyVFJVZ__Latest.json",
      "kind": "file",
      "label": "inputs/ghl/GHLConversations__JH4o9LqPhHyuvvyVFJVZ__Latest.json",
      "source": "ghl"
    },
    {
      "extension": ".json",
      "id": "file:inputs/ghl/GHLCustomFields__JH4o9LqPhHyuvvyVFJVZ__Latest.json",
      "kind": "file",
      "label": "inputs/ghl/GHLCustomFields__JH4o9LqPhHyuvvyVFJVZ__Latest.json",
      "source": "ghl"
    },
    {
      "extension": ".json",
      "id": "file:inputs/ghl/GHLCustomValues__JH4o9LqPhHyuvvyVFJVZ__Latest.json",
      "kind": "file",
      "label": "inputs/ghl/GHLCustomValues__JH4o9LqPhHyuvvyVFJVZ__Latest.json",
      "source": "ghl"
    },
    {
      "extension": ".json",
      "id": "file:inputs/ghl/GHLEmailTemplates__JH4o9LqPhHyuvvyVFJVZ__Latest.json",
      "kind": "file",
      "label": "inputs/ghl/GHLEmailTemplates__JH4o9LqPhHyuvvyVFJVZ__Latest.json",
      "source": "ghl"
    },
    {
      "extension": ".json",
      "id": "file:inputs/ghl/GHLForms__JH4o9LqPhHyuvvyVFJVZ__Latest.json",
      "kind": "file",
      "label": "inputs/ghl/GHLForms__JH4o9LqPhHyuvvyVFJVZ__Latest.json",
      "source": "ghl"
    },
    {
      "extension": ".json",
      "id": "file:inputs/ghl/GHLFunnels__JH4o9LqPhHyuvvyVFJVZ__Latest.json",
      "kind": "file",
      "label": "inputs/ghl/GHLFunnels__JH4o9LqPhHyuvvyVFJVZ__Latest.json",
      "source": "ghl"
    },
    {
      "extension": ".json",
      "id": "file:inputs/ghl/GHLLocation__JH4o9LqPhHyuvvyVFJVZ__Latest.json",
      "kind": "file",
      "label": "inputs/ghl/GHLLocation__JH4o9LqPhHyuvvyVFJVZ__Latest.json",
      "source": "ghl"
    },
    {
      "extension": ".json",
      "id": "file:inputs/ghl/GHLPipelines__JH4o9LqPhHyuvvyVFJVZ__Latest.json",
      "kind": "file",
      "label": "inputs/ghl/GHLPipelines__JH4o9LqPhHyuvvyVFJVZ__Latest.json",
      "source": "ghl"
    },
    {
      "extension": ".json",
      "id": "file:inputs/ghl/GHLTags__JH4o9LqPhHyuvvyVFJVZ__Latest.json",
      "kind": "file",
      "label": "inputs/ghl/GHLTags__JH4o9LqPhHyuvvyVFJVZ__Latest.json",
      "source": "ghl"
    },
    {
      "extension": ".json",
      "id": "file:inputs/ghl/GHLTriggerLinks__JH4o9LqPhHyuvvyVFJVZ__Latest.json",
      "kind": "file",
      "label": "inputs/ghl/GHLTriggerLinks__JH4o9LqPhHyuvvyVFJVZ__Latest.json",
      "source": "ghl"
    },
    {
      "extension": ".json",
      "id": "file:inputs/ghl/GHLUsers__JH4o9LqPhHyuvvyVFJVZ__Latest.json",
      "kind": "file",
      "label": "inputs/ghl/GHLUsers__JH4o9LqPhHyuvvyVFJVZ__Latest.json",
      "source": "ghl"
    },
    {
      "extension": ".json",
      "id": "file:inputs/ghl/GHLWorkflow__82cb0414-c64a-4fdd-8961-96719dea3878__Latest.json",
      "kind": "file",
      "label": "inputs/ghl/GHLWorkflow__82cb0414-c64a-4fdd-8961-96719dea3878__Latest.json",
      "source": "ghl"
    },
    {
      "extension": ".json",
      "id": "file:inputs/ghl/GHLWorkflow__90cecd4e-e701-46bb-87c5-9aa43c2b0ea5__Latest.json",
      "kind": "file",
      "label": "inputs/ghl/GHLWorkflow__90cecd4e-e701-46bb-87c5-9aa43c2b0ea5__Latest.json",
      "source": "ghl"
    },
    {
      "extension": ".json",
      "id": "file:inputs/ghl/GHLWorkflows__JH4o9LqPhHyuvvyVFJVZ__Latest.json",
      "kind": "file",
      "label": "inputs/ghl/GHLWorkflows__JH4o9LqPhHyuvvyVFJVZ__Latest.json",
      "source": "ghl"
    },
    {
      "extension": ".md",
      "id": "file:inputs/ghl/README.md",
      "kind": "file",
      "label": "inputs/ghl/README.md",
      "source": "ghl"
    },
    {
      "extension": ".json",
      "id": "file:inputs/make/MAKE_SCENARIOS.json",
      "kind": "file",
      "label": "inputs/make/MAKE_SCENARIOS.json",
      "source": "make"
    },
    {
      "extension": ".json",
      "id": "file:inputs/make/MAKE_SCENARIO_INDEX__Latest.json",
      "kind": "file",
      "label": "inputs/make/MAKE_SCENARIO_INDEX__Latest.json",
      "source": "make"
    },
    {
      "extension": ".json",
      "id": "file:inputs/make/MAKE_SCENARIO_LISTING__Latest.json",
      "kind": "file",
      "label": "inputs/make/MAKE_SCENARIO_LISTING__Latest.json",
      "source": "make"
    },
    {
      "extension": ".json",
      "id": "file:inputs/make/MakeProbe__Latest.json",
      "kind": "file",
      "label": "inputs/make/MakeProbe__Latest.json",
      "source": "make"
    },
    {
      "extension": ".md",
      "id": "file:inputs/make/README.md",
      "kind": "file",
      "label": "inputs/make/README.md",
      "source": "make"
    },
    {
      "extension": ".json",
      "id": "file:inputs/make/blueprints/MakeBlueprint__2348337__Latest.json",
      "kind": "file",
      "label": "inputs/make/blueprints/MakeBlueprint__2348337__Latest.json",
      "source": "make"
    },
    {
      "extension": ".json",
      "id": "file:inputs/make/blueprints/MakeBlueprint__3664392__Latest.json",
      "kind": "file",
      "label": "inputs/make/blueprints/MakeBlueprint__3664392__Latest.json",
      "source": "make"
    },
    {
      "extension": ".json",
      "id": "file:inputs/make/blueprints/MakeBlueprint__3673026__Latest.json",
      "kind": "file",
      "label": "inputs/make/blueprints/MakeBlueprint__3673026__Latest.json",
      "source": "make"
    },
    {
      "extension": ".json",
      "id": "file:inputs/make/blueprints/MakeBlueprint__3686763__Latest.json",
      "kind": "file",
      "label": "inputs/make/blueprints/MakeBlueprint__3686763__Latest.json",
      "source": "make"
    },
    {
      "extension": ".json",
      "id": "file:inputs/make/blueprints/MakeBlueprint__3686991__Latest.json",
      "kind": "file",
      "label": "inputs/make/blueprints/MakeBlueprint__3686991__Latest.json",
      "source": "make"
    },
    {
      "extension": ".json",
      "id": "file:inputs/make/blueprints/MakeBlueprint__3687011__Latest.json",
      "kind": "file",
      "label": "inputs/make/blueprints/MakeBlueprint__3687011__Latest.json",
      "source": "make"
    },
    {
      "extension": ".json",
      "id": "file:inputs/make/blueprints/MakeBlueprint__3733465__Latest.json",
      "kind": "file",
      "label": "inputs/make/blueprints/MakeBlueprint__3733465__Latest.json",
      "source": "make"
    },
    {
      "extension": ".json",
      "id": "file:inputs/make/blueprints/MakeBlueprint__3738189__Latest.json",
      "kind": "file",
      "label": "inputs/make/blueprints/MakeBlueprint__3738189__Latest.json",
      "source": "make"
    },
    {
      "extension": ".json",
      "id": "file:inputs/make/blueprints/MakeBlueprint__3744510__Latest.json",
      "kind": "file",
      "label": "inputs/make/blueprints/MakeBlueprint__3744510__Latest.json",
      "source": "make"
    },
    {
      "extension": ".json",
      "id": "file:inputs/make/blueprints/MakeBlueprint__3745933__Latest.json",
      "kind": "file",
      "label": "inputs/make/blueprints/MakeBlueprint__3745933__Latest.json",
      "source": "make"
    },
    {
      "extension": ".json",
      "id": "file:inputs/make/blueprints/MakeBlueprint__3761572__Latest.json",
      "kind": "file",
      "label": "inputs/make/blueprints/MakeBlueprint__3761572__Latest.json",
      "source": "make"
    },
    {
      "extension": ".json",
      "id": "file:inputs/make/blueprints/MakeBlueprint__3795815__Latest.json",
      "kind": "file",
      "label": "inputs/make/blueprints/MakeBlueprint__3795815__Latest.json",
      "source": "make"
    },
    {
      "extension": ".json",
      "id": "file:inputs/make/blueprints/MakeBlueprint__3798600__Latest.json",
      "kind": "file",
      "label": "inputs/make/blueprints/MakeBlueprint__3798600__Latest.json",
      "source": "make"
    },
    {
      "extension": ".json",
      "id": "file:inputs/make/blueprints/MakeBlueprint__3818644__Latest.json",
      "kind": "file",
      "label": "inputs/make/blueprints/MakeBlueprint__3818644__Latest.json",
      "source": "make"
    },
    {
      "extension": ".json",
      "id": "file:inputs/make/blueprints/MakeBlueprint__3818650__Latest.json",
      "kind": "file",
      "label": "inputs/make/blueprints/MakeBlueprint__3818650__Latest.json",
      "source": "make"
    },
    {
      "extension": ".json",
      "id": "file:inputs/make/blueprints/MakeBlueprint__3818652__Latest.json",
      "kind": "file",
      "label": "inputs/make/blueprints/MakeBlueprint__3818652__Latest.json",
      "source": "make"
    },
    {
      "extension": ".json",
      "id": "file:inputs/make/blueprints/MakeBlueprint__3818663__Latest.json",
      "kind": "file",
      "label": "inputs/make/blueprints/MakeBlueprint__3818663__Latest.json",
      "source": "make"
    },
    {
      "extension": ".json",
      "id": "file:inputs/make/blueprints/MakeBlueprint__3824254__Latest.json",
      "kind": "file",
      "label": "inputs/make/blueprints/MakeBlueprint__3824254__Latest.json",
      "source": "make"
    },
    {
      "extension": ".json",
      "id": "file:inputs/make/blueprints/MakeBlueprint__3824833__Latest.json",
      "kind": "file",
      "label": "inputs/make/blueprints/MakeBlueprint__3824833__Latest.json",
      "source": "make"
    },
    {
      "extension": ".json",
      "id": "file:inputs/make/blueprints/MakeBlueprint__3859876__Latest.json",
      "kind": "file",
      "label": "inputs/make/blueprints/MakeBlueprint__3859876__Latest.json",
      "source": "make"
    },
    {
      "extension": ".json",
      "id": "file:inputs/make/blueprints/MakeBlueprint__3920516__Latest.json",
      "kind": "file",
      "label": "inputs/make/blueprints/MakeBlueprint__3920516__Latest.json",
      "source": "make"
    },
    {
      "extension": ".json",
      "id": "file:inputs/make/blueprints/MakeBlueprint__3920818__Latest.json",
      "kind": "file",
      "label": "inputs/make/blueprints/MakeBlueprint__3920818__Latest.json",
      "source": "make"
    },
    {
      "extension": ".json",
      "id": "file:inputs/make/blueprints/MakeBlueprint__3952284__Latest.json",
      "kind": "file",
      "label": "inputs/make/blueprints/MakeBlueprint__3952284__Latest.json",
      "source": "make"
    },
    {
      "extension": ".json",
      "id": "file:inputs/make/blueprints/MakeBlueprint__3961170__Latest.json",
      "kind": "file",
      "label": "inputs/make/blueprints/MakeBlueprint__3961170__Latest.json",
      "source": "make"
    },
    {
      "extension": ".json",
      "id": "file:inputs/make/blueprints/MakeBlueprint__3996198__Latest.json",
      "kind": "file",
      "label": "inputs/make/blueprints/MakeBlueprint__3996198__Latest.json",
      "source": "make"
    },
    {
      "extension": ".json",
      "id": "file:inputs/make/blueprints/MakeBlueprint__4001823__Latest.json",
      "kind": "file",
      "label": "inputs/make/blueprints/MakeBlueprint__4001823__Latest.json",
      "source": "make"
    },
    {
      "extension": ".json",
      "id": "file:inputs/make/blueprints/MakeBlueprint__4002164__Latest.json",
      "kind": "file",
      "label": "inputs/make/blueprints/MakeBlueprint__4002164__Latest.json",
      "source": "make"
    },
    {
      "extension": ".json",
      "id": "file:inputs/make/blueprints/MakeBlueprint__4002272__Latest.json",
      "kind": "file",
      "label": "inputs/make/blueprints/MakeBlueprint__4002272__Latest.json",
      "source": "make"
    },
    {
      "extension": ".json",
      "id": "file:inputs/make/blueprints/MakeBlueprint__4055279__Latest.json",
      "kind": "file",
      "label": "inputs/make/blueprints/MakeBlueprint__4055279__Latest.json",
      "source": "make"
    },
    {
      "extension": ".json",
      "id": "file:inputs/make/blueprints/MakeBlueprint__4055283__Latest.json",
      "kind": "file",
      "label": "inputs/make/blueprints/MakeBlueprint__4055283__Latest.json",
      "source": "make"
    },
    {
      "extension": ".json",
      "id": "file:inputs/make/blueprints/MakeBlueprint__4091455__Latest.json",
      "kind": "file",
      "label": "inputs/make/blueprints/MakeBlueprint__4091455__Latest.json",
      "source": "make"
    },
    {
      "extension": ".json",
      "id": "file:inputs/make/blueprints/MakeBlueprint__4091456__Latest.json",
      "kind": "file",
      "label": "inputs/make/blueprints/MakeBlueprint__4091456__Latest.json",
      "source": "make"
    },
    {
      "extension": ".json",
      "id": "file:inputs/make/blueprints/MakeBlueprint__4093385__Latest.json",
      "kind": "file",
      "label": "inputs/make/blueprints/MakeBlueprint__4093385__Latest.json",
      "source": "make"
    },
    {
      "extension": ".json",
      "id": "file:inputs/make/blueprints/MakeBlueprint__4121916__Latest.json",
      "kind": "file",
      "label": "inputs/make/blueprints/MakeBlueprint__4121916__Latest.json",
      "source": "make"
    },
    {
      "extension": ".json",
      "id": "file:inputs/make/blueprints/MakeBlueprint__4123962__Latest.json",
      "kind": "file",
      "label": "inputs/make/blueprints/MakeBlueprint__4123962__Latest.json",
      "source": "make"
    },
    {
      "extension": ".json",
      "id": "file:inputs/make/blueprints/MakeBlueprint__4124710__Latest.json",
      "kind": "file",
      "label": "inputs/make/blueprints/MakeBlueprint__4124710__Latest.json",
      "source": "make"
    },
    {
      "extension": ".json",
      "id": "file:inputs/make/blueprints/MakeBlueprint__4127837__Latest.json",
      "kind": "file",
      "label": "inputs/make/blueprints/MakeBlueprint__4127837__Latest.json",
      "source": "make"
    },
    {
      "extension": ".json",
      "id": "file:inputs/make/blueprints/MakeBlueprint__4128249__Latest.json",
      "kind": "file",
      "label": "inputs/make/blueprints/MakeBlueprint__4128249__Latest.json",
      "source": "make"
    },
    {
      "extension": ".json",
      "id": "file:inputs/make/blueprints/MakeBlueprint__4128593__Latest.json",
      "kind": "file",
      "label": "inputs/make/blueprints/MakeBlueprint__4128593__Latest.json",
      "source": "make"
    },
    {
      "extension": ".json",
      "id": "file:inputs/make/blueprints/MakeBlueprint__4148204__Latest.json",
      "kind": "file",
      "label": "inputs/make/blueprints/MakeBlueprint__4148204__Latest.json",
      "source": "make"
    },
    {
      "extension": ".json",
      "id": "file:inputs/make/blueprints/MakeBlueprint__4185478__Latest.json",
      "kind": "file",
      "label": "inputs/make/blueprints/MakeBlueprint__4185478__Latest.json",
      "source": "make"
    },
    {
      "extension": ".json",
      "id": "file:inputs/make/blueprints/MakeBlueprint__4206316__Latest.json",
      "kind": "file",
      "label": "inputs/make/blueprints/MakeBlueprint__4206316__Latest.json",
      "source": "make"
    },
    {
      "extension": ".json",
      "id": "file:inputs/make/blueprints/MakeBlueprint__4207345__Latest.json",
      "kind": "file",
      "label": "inputs/make/blueprints/MakeBlueprint__4207345__Latest.json",
      "source": "make"
    },
    {
      "extension": ".json",
      "id": "file:inputs/make/blueprints/MakeBlueprint__4226576__Latest.json",
      "kind": "file",
      "label": "inputs/make/blueprints/MakeBlueprint__4226576__Latest.json",
      "source": "make"
    },
    {
      "extension": ".json",
      "id": "file:inputs/make/blueprints/MakeBlueprint__4227392__Latest.json",
      "kind": "file",
      "label": "inputs/make/blueprints/MakeBlueprint__4227392__Latest.json",
      "source": "make"
    },
    {
      "extension": ".json",
      "id": "file:inputs/make/blueprints/MakeBlueprint__4265554__Latest.json",
      "kind": "file",
      "label": "inputs/make/blueprints/MakeBlueprint__4265554__Latest.json",
      "source": "make"
    },
    {
      "extension": ".json",
      "id": "file:inputs/make/blueprints/MakeBlueprint__4267051__Latest.json",
      "kind": "file",
      "label": "inputs/make/blueprints/MakeBlueprint__4267051__Latest.json",
      "source": "make"
    },
    {
      "extension": ".json",
      "id": "file:inputs/make/blueprints/MakeBlueprint__4267120__Latest.json",
      "kind": "file",
      "label": "inputs/make/blueprints/MakeBlueprint__4267120__Latest.json",
      "source": "make"
    },
    {
      "extension": ".json",
      "id": "file:inputs/make/blueprints/MakeBlueprint__4328562__Latest.json",
      "kind": "file",
      "label": "inputs/make/blueprints/MakeBlueprint__4328562__Latest.json",
      "source": "make"
    },
    {
      "extension": ".json",
      "id": "file:inputs/make/blueprints/MakeBlueprint__4347798__Latest.json",
      "kind": "file",
      "label": "inputs/make/blueprints/MakeBlueprint__4347798__Latest.json",
      "source": "make"
    },
    {
      "extension": ".json",
      "id": "file:inputs/make/blueprints/MakeBlueprint__4360004__Latest.json",
      "kind": "file",
      "label": "inputs/make/blueprints/MakeBlueprint__4360004__Latest.json",
      "source": "make"
    },
    {
      "extension": ".md",
      "id": "file:inputs/make/blueprints/README.md",
      "kind": "file",
      "label": "inputs/make/blueprints/README.md",
      "source": "make"
    },
    {
      "extension": ".md",
      "id": "file:inputs/make/digests/MakeDigest__C12IntelReportDigest__3798600__v0.1.json.md",
      "kind": "file",
      "label": "inputs/make/digests/MakeDigest__C12IntelReportDigest__3798600__v0.1.json.md",
      "source": "make"
    },
    {
      "extension": ".md",
      "id": "file:inputs/make/digests/MakeDigest__EmailConveyor__4093385__2026-02-12T15-09-37.json.md",
      "kind": "file",
      "label": "inputs/make/digests/MakeDigest__EmailConveyor__4093385__2026-02-12T15-09-37.json.md",
      "source": "make"
    },
    {
      "extension": ".md",
      "id": "file:inputs/make/digests/MakeDigest__IntelConveyor__4091455__v0.1.json.md",
      "kind": "file",
      "label": "inputs/make/digests/MakeDigest__IntelConveyor__4091455__v0.1.json.md",
      "source": "make"
    },
    {
      "extension": ".md",
      "id": "file:inputs/make/digests/README.md",
      "kind": "file",
      "label": "inputs/make/digests/README.md",
      "source": "make"
    },
    {
      "extension": ".md",
      "id": "file:inputs/models/system/index.md",
      "kind": "file",
      "label": "inputs/models/system/index.md",
      "source": "models"
    },
    {
      "extension": ".md",
      "id": "file:inputs/qb/QB Centurion Intel SEED (1).md",
      "kind": "file",
      "label": "inputs/qb/QB Centurion Intel SEED (1).md",
      "source": "qb"
    },
    {
      "extension": ".md",
      "id": "file:inputs/qb/QB__CenturionIntel__v0.3.md",
      "kind": "file",
      "label": "inputs/qb/QB__CenturionIntel__v0.3.md",
      "source": "qb"
    },
    {
      "extension": ".md",
      "id": "file:inputs/qb/README.md",
      "kind": "file",
      "label": "inputs/qb/README.md",
      "source": "qb"
    },
    {
      "extension": ".md",
      "id": "file:inputs/snapshots/index.md",
      "kind": "file",
      "label": "inputs/snapshots/index.md",
      "source": "snapshots"
    },
    {
      "extension": ".md",
      "id": "file:inputs/softr/README.md",
      "kind": "file",
      "label": "inputs/softr/README.md",
      "source": "softr"
    },
    {
      "extension": ".json",
      "id": "file:inputs/softr/SoftrUsers__Latest.json",
      "kind": "file",
      "label": "inputs/softr/SoftrUsers__Latest.json",
      "source": "softr"
    },
    {
      "extension": ".md",
      "id": "file:inputs/videoask/README.md",
      "kind": "file",
      "label": "inputs/videoask/README.md",
      "source": "videoask"
    },
    {
      "extension": ".json",
      "id": "file:inputs/videoask/VideoAskForms__Latest.json",
      "kind": "file",
      "label": "inputs/videoask/VideoAskForms__Latest.json",
      "source": "videoask"
    },
    {
      "extension": ".md",
      "id": "file:inputs/videopeel/readme.md",
      "kind": "file",
      "label": "inputs/videopeel/readme.md",
      "source": "videopeel"
    },
    {
      "extension": ".md",
      "id": "file:inputs/web/readme.md",
      "kind": "file",
      "label": "inputs/web/readme.md",
      "source": "web"
    }
  ],
  "schema_version": 1
}
