{
  "edges": [
    {
      "from": "atlas",
      "relation": "ingests",
      "to": "source:airtable"
    },
    {
      "from": "atlas",
      "relation": "ingests",
      "to": "source:changelog"
    },
    {
      "from": "atlas",
      "relation": "ingests",
      "to": "source:clay"
    },
    {
      "from": "atlas",
      "relation": "ingests",
      "to": "source:ghl"
    },
    {
      "from": "atlas",
      "relation": "ingests",
      "to": "source:make"
    },
    {
      "from": "atlas",
      "relation": "ingests",
      "to": "source:models"
    },
    {
      "from": "atlas",
      "relation": "ingests",
      "to": "source:qb"
    },
    {
      "from": "atlas",
      "relation": "ingests",
      "to": "source:root"
    },
    {
      "from": "atlas",
      "relation": "ingests",
      "to": "source:snapshots"
    },
    {
      "from": "atlas",
      "relation": "ingests",
      "to": "source:softr"
    },
    {
      "from": "atlas",
      "relation": "ingests",
      "to": "source:videoask"
    },
    {
      "from": "atlas",
      "relation": "ingests",
      "to": "source:videopeel"
    },
    {
      "from": "atlas",
      "relation": "ingests",
      "to": "source:web"
    },
    {
      "from": "source:root",
      "relation": "contains",
      "to": "file:inputs/README.md"
    },
    {
      "from": "source:airtable",
      "relation": "contains",
      "to": "file:inputs/airtable/Airtable \u00b7 Dancing King Client Vault \u00b7 System Map \u00b7 v0.md"
    },
    {
      "from": "source:airtable",
      "relation": "contains",
      "to": "file:inputs/airtable/AirtableSchema__DancingKingClientVault__2026-02-12T14_19_55.058Z.json.docx"
    },
    {
      "from": "source:airtable",
      "relation": "contains",
      "to": "file:inputs/airtable/AirtableSchema__DancingKingClientVault__Latest.json"
    },
    {
      "from": "source:airtable",
      "relation": "contains",
      "to": "file:inputs/airtable/AirtableSchema__app0ezVqvqQRWTXIJ__Latest.json"
    },
    {
      "from": "source:airtable",
      "relation": "contains",
      "to": "file:inputs/airtable/AirtableSchema__appQFyu6Aejoq7yHP__Latest.json"
    },
    {
      "from": "source:airtable",
      "relation": "contains",
      "to": "file:inputs/airtable/README.md"
    },
    {
      "from": "source:changelog",
      "relation": "contains",
      "to": "file:inputs/changelog/index.md"
    },
    {
      "from": "source:clay",
      "relation": "contains",
      "to": "file:inputs/clay/README.md"
    },
    {
      "from": "source:ghl",
      "relation": "contains",
      "to": "file:inputs/ghl/GHLCalendars__JH4o9LqPhHyuvvyVFJVZ__Latest.json"
    },
    {
      "from": "source:ghl",
      "relation": "contains",
      "to": "file:inputs/ghl/GHLContacts__JH4o9LqPhHyuvvyVFJVZ__Latest.json"
    },
    {
      "from": "source:ghl",
      "relation": "contains",
      "to": "file:inputs/ghl/GHLConversations__JH4o9LqPhHyuvvyVFJVZ__Latest.json"
    },
    {
      "from": "source:ghl",
      "relation": "contains",
      "to": "file:inputs/ghl/GHLCustomFields__JH4o9LqPhHyuvvyVFJVZ__Latest.json"
    },
    {
      "from": "source:ghl",
      "relation": "contains",
      "to": "file:inputs/ghl/GHLCustomValues__JH4o9LqPhHyuvvyVFJVZ__Latest.json"
    },
    {
      "from": "source:ghl",
      "relation": "contains",
      "to": "file:inputs/ghl/GHLEmailTemplates__JH4o9LqPhHyuvvyVFJVZ__Latest.json"
    },
    {
      "from": "source:ghl",
      "relation": "contains",
      "to": "file:inputs/ghl/GHLForms__JH4o9LqPhHyuvvyVFJVZ__Latest.json"
    },
    {
      "from": "source:ghl",
      "relation": "contains",
      "to": "file:inputs/ghl/GHLFunnels__JH4o9LqPhHyuvvyVFJVZ__Latest.json"
    },
    {
      "from": "source:ghl",
      "relation": "contains",
      "to": "file:inputs/ghl/GHLLocation__JH4o9LqPhHyuvvyVFJVZ__Latest.json"
    },
    {
      "from": "source:ghl",
      "relation": "contains",
      "to": "file:inputs/ghl/GHLPipelines__JH4o9LqPhHyuvvyVFJVZ__Latest.json"
    },
    {
      "from": "source:ghl",
      "relation": "contains",
      "to": "file:inputs/ghl/GHLTags__JH4o9LqPhHyuvvyVFJVZ__Latest.json"
    },
    {
      "from": "source:ghl",
      "relation": "contains",
      "to": "file:inputs/ghl/GHLTriggerLinks__JH4o9LqPhHyuvvyVFJVZ__Latest.json"
    },
    {
      "from": "source:ghl",
      "relation": "contains",
      "to": "file:inputs/ghl/GHLUsers__JH4o9LqPhHyuvvyVFJVZ__Latest.json"
    },
    {
      "from": "source:ghl",
      "relation": "contains",
      "to": "file:inputs/ghl/GHLWorkflow__82cb0414-c64a-4fdd-8961-96719dea3878__Latest.json"
    },
    {
      "from": "source:ghl",
      "relation": "contains",
      "to": "file:inputs/ghl/GHLWorkflow__90cecd4e-e701-46bb-87c5-9aa43c2b0ea5__Latest.json"
    },
    {
      "from": "source:ghl",
      "relation": "contains",
      "to": "file:inputs/ghl/GHLWorkflows__JH4o9LqPhHyuvvyVFJVZ__Latest.json"
    },
    {
      "from": "source:ghl",
      "relation": "contains",
      "to": "file:inputs/ghl/README.md"
    },
    {
      "from": "source:make",
      "relation": "contains",
      "to": "file:inputs/make/MAKE_SCENARIOS.json"
    },
    {
      "from": "source:make",
      "relation": "contains",
      "to": "file:inputs/make/MAKE_SCENARIO_INDEX__Latest.json"
    },
    {
      "from": "source:make",
      "relation": "contains",
      "to": "file:inputs/make/MAKE_SCENARIO_LISTING__Latest.json"
    },
    {
      "from": "source:make",
      "relation": "contains",
      "to": "file:inputs/make/MakeProbe__Latest.json"
    },
    {
      "from": "source:make",
      "relation": "contains",
      "to": "file:inputs/make/README.md"
    },
    {
      "from": "source:make",
      "relation": "contains",
      "to": "file:inputs/make/blueprints/MakeBlueprint__2348337__Latest.json"
    },
    {
      "from": "source:make",
      "relation": "contains",
      "to": "file:inputs/make/blueprints/MakeBlueprint__3664392__Latest.json"
    },
    {
      "from": "source:make",
      "relation": "contains",
      "to": "file:inputs/make/blueprints/MakeBlueprint__3673026__Latest.json"
    },
    {
      "from": "source:make",
      "relation": "contains",
      "to": "file:inputs/make/blueprints/MakeBlueprint__3686763__Latest.json"
    },
    {
      "from": "source:make",
      "relation": "contains",
      "to": "file:inputs/make/blueprints/MakeBlueprint__3686991__Latest.json"
    },
    {
      "from": "source:make",
      "relation": "contains",
      "to": "file:inputs/make/blueprints/MakeBlueprint__3687011__Latest.json"
    },
    {
      "from": "source:make",
      "relation": "contains",
      "to": "file:inputs/make/blueprints/MakeBlueprint__3733465__Latest.json"
    },
    {
      "from": "source:make",
      "relation": "contains",
      "to": "file:inputs/make/blueprints/MakeBlueprint__3738189__Latest.json"
    },
    {
      "from": "source:make",
      "relation": "contains",
      "to": "file:inputs/make/blueprints/MakeBlueprint__3744510__Latest.json"
    },
    {
      "from": "source:make",
      "relation": "contains",
      "to": "file:inputs/make/blueprints/MakeBlueprint__3745933__Latest.json"
    },
    {
      "from": "source:make",
      "relation": "contains",
      "to": "file:inputs/make/blueprints/MakeBlueprint__3761572__Latest.json"
    },
    {
      "from": "source:make",
      "relation": "contains",
      "to": "file:inputs/make/blueprints/MakeBlueprint__3795815__Latest.json"
    },
    {
      "from": "source:make",
      "relation": "contains",
      "to": "file:inputs/make/blueprints/MakeBlueprint__3798600__Latest.json"
    },
    {
      "from": "source:make",
      "relation": "contains",
      "to": "file:inputs/make/blueprints/MakeBlueprint__3818644__Latest.json"
    },
    {
      "from": "source:make",
      "relation": "contains",
      "to": "file:inputs/make/blueprints/MakeBlueprint__3818650__Latest.json"
    },
    {
      "from": "source:make",
      "relation": "contains",
      "to": "file:inputs/make/blueprints/MakeBlueprint__3818652__Latest.json"
    },
    {
      "from": "source:make",
      "relation": "contains",
      "to": "file:inputs/make/blueprints/MakeBlueprint__3818663__Latest.json"
    },
    {
      "from": "source:make",
      "relation": "contains",
      "to": "file:inputs/make/blueprints/MakeBlueprint__3824254__Latest.json"
    },
    {
      "from": "source:make",
      "relation": "contains",
      "to": "file:inputs/make/blueprints/MakeBlueprint__3824833__Latest.json"
    },
    {
      "from": "source:make",
      "relation": "contains",
      "to": "file:inputs/make/blueprints/MakeBlueprint__3859876__Latest.json"
    },
    {
      "from": "source:make",
      "relation": "contains",
      "to": "file:inputs/make/blueprints/MakeBlueprint__3920516__Latest.json"
    },
    {
      "from": "source:make",
      "relation": "contains",
      "to": "file:inputs/make/blueprints/MakeBlueprint__3920818__Latest.json"
    },
    {
      "from": "source:make",
      "relation": "contains",
      "to": "file:inputs/make/blueprints/MakeBlueprint__3952284__Latest.json"
    },
    {
      "from": "source:make",
      "relation": "contains",
      "to": "file:inputs/make/blueprints/MakeBlueprint__3961170__Latest.json"
    },
    {
      "from": "source:make",
      "relation": "contains",
      "to": "file:inputs/make/blueprints/MakeBlueprint__3996198__Latest.json"
    },
    {
      "from": "source:make",
      "relation": "contains",
      "to": "file:inputs/make/blueprints/MakeBlueprint__4001823__Latest.json"
    },
    {
      "from": "source:make",
      "relation": "contains",
      "to": "file:inputs/make/blueprints/MakeBlueprint__4002164__Latest.json"
    },
    {
      "from": "source:make",
      "relation": "contains",
      "to": "file:inputs/make/blueprints/MakeBlueprint__4002272__Latest.json"
    },
    {
      "from": "source:make",
      "relation": "contains",
      "to": "file:inputs/make/blueprints/MakeBlueprint__4055279__Latest.json"
    },
    {
      "from": "source:make",
      "relation": "contains",
      "to": "file:inputs/make/blueprints/MakeBlueprint__4055283__Latest.json"
    },
    {
      "from": "source:make",
      "relation": "contains",
      "to": "file:inputs/make/blueprints/MakeBlueprint__4091455__Latest.json"
    },
    {
      "from": "source:make",
      "relation": "contains",
      "to": "file:inputs/make/blueprints/MakeBlueprint__4091456__Latest.json"
    },
    {
      "from": "source:make",
      "relation": "contains",
      "to": "file:inputs/make/blueprints/MakeBlueprint__4093385__Latest.json"
    },
    {
      "from": "source:make",
      "relation": "contains",
      "to": "file:inputs/make/blueprints/MakeBlueprint__4121916__Latest.json"
    },
    {
      "from": "source:make",
      "relation": "contains",
      "to": "file:inputs/make/blueprints/MakeBlueprint__4123962__Latest.json"
    },
    {
      "from": "source:make",
      "relation": "contains",
      "to": "file:inputs/make/blueprints/MakeBlueprint__4124710__Latest.json"
    },
    {
      "from": "source:make",
      "relation": "contains",
      "to": "file:inputs/make/blueprints/MakeBlueprint__4127837__Latest.json"
    },
    {
      "from": "source:make",
      "relation": "contains",
      "to": "file:inputs/make/blueprints/MakeBlueprint__4128249__Latest.json"
    },
    {
      "from": "source:make",
      "relation": "contains",
      "to": "file:inputs/make/blueprints/MakeBlueprint__4128593__Latest.json"
    },
    {
      "from": "source:make",
      "relation": "contains",
      "to": "file:inputs/make/blueprints/MakeBlueprint__4148204__Latest.json"
    },
    {
      "from": "source:make",
      "relation": "contains",
      "to": "file:inputs/make/blueprints/MakeBlueprint__4185478__Latest.json"
    },
    {
      "from": "source:make",
      "relation": "contains",
      "to": "file:inputs/make/blueprints/MakeBlueprint__4206316__Latest.json"
    },
    {
      "from": "source:make",
      "relation": "contains",
      "to": "file:inputs/make/blueprints/MakeBlueprint__4207345__Latest.json"
    },
    {
      "from": "source:make",
      "relation": "contains",
      "to": "file:inputs/make/blueprints/MakeBlueprint__4226576__Latest.json"
    },
    {
      "from": "source:make",
      "relation": "contains",
      "to": "file:inputs/make/blueprints/MakeBlueprint__4227392__Latest.json"
    },
    {
      "from": "source:make",
      "relation": "contains",
      "to": "file:inputs/make/blueprints/MakeBlueprint__4265554__Latest.json"
    },
    {
      "from": "source:make",
      "relation": "contains",
      "to": "file:inputs/make/blueprints/MakeBlueprint__4267051__Latest.json"
    },
    {
      "from": "source:make",
      "relation": "contains",
      "to": "file:inputs/make/blueprints/MakeBlueprint__4267120__Latest.json"
    },
    {
      "from": "source:make",
      "relation": "contains",
      "to": "file:inputs/make/blueprints/MakeBlueprint__4328562__Latest.json"
    },
    {
      "from": "source:make",
      "relation": "contains",
      "to": "file:inputs/make/blueprints/MakeBlueprint__4347798__Latest.json"
    },
    {
      "from": "source:make",
      "relation": "contains",
      "to": "file:inputs/make/blueprints/MakeBlueprint__4360004__Latest.json"
    },
    {
      "from": "source:make",
      "relation": "contains",
      "to": "file:inputs/make/blueprints/README.md"
    },
    {
      "from": "source:make",
      "relation": "contains",
      "to": "file:inputs/make/digests/MakeDigest__C12IntelReportDigest__3798600__v0.1.json.md"
    },
    {
      "from": "source:make",
      "relation": "contains",
      "to": "file:inputs/make/digests/MakeDigest__EmailConveyor__4093385__2026-02-12T15-09-37.json.md"
    },
    {
      "from": "source:make",
      "relation": "contains",
      "to": "file:inputs/make/digests/MakeDigest__IntelConveyor__4091455__v0.1.json.md"
    },
    {
      "from": "source:make",
      "relation": "contains",
      "to": "file:inputs/make/digests/README.md"
    },
    {
      "from": "source:models",
      "relation": "contains",
      "to": "file:inputs/models/system/index.md"
    },
    {
      "from": "source:qb",
      "relation": "contains",
      "to": "file:inputs/qb/QB Centurion Intel SEED (1).md"
    },
    {
      "from": "source:qb",
      "relation": "contains",
      "to": "file:inputs/qb/QB__CenturionIntel__v0.3.md"
    },
    {
      "from": "source:qb",
      "relation": "contains",
      "to": "file:inputs/qb/README.md"
    },
    {
      "from": "source:snapshots",
      "relation": "contains",
      "to": "file:inputs/snapshots/index.md"
    },
    {
      "from": "source:softr",
      "relation": "contains",
      "to": "file:inputs/softr/README.md"
    },
    {
      "from": "source:softr",
      "relation": "contains",
      "to": "file:inputs/softr/SoftrUsers__Latest.json"
    },
    {
      "from": "source:videoask",
      "relation": "contains",
      "to": "file:inputs/videoask/README.md"
    },
    {
      "from": "source:videoask",
      "relation": "contains",
      "to": "file:inputs/videoask/VideoAskForms__Latest.json"
    },
    {
      "from": "source:videopeel",
      "relation": "contains",
      "to": "file:inputs/videopeel/readme.md"
    },
    {
      "from": "source:web",
      "relation": "contains",
      "to": "file:inputs/web/readme.md"
    }
  ],
  "files": [
    {
      "extension": ".md",
      "json_top_level_keys": "UNKNOWN",
      "markdown_heading": "UNKNOWN",
      "path": "inputs/README.md",
      "sha256": "71f075203fe6ef1fe6d6c3bdeb265941ce42041c728f1d4b36e47b7cc13a509d",
      "size_bytes": 40,
      "source": "root"
    },
    {
      "extension": ".md",
      "json_top_level_keys": "UNKNOWN",
      "markdown_heading": "**Tables overview**",
      "path": "inputs/airtable/Airtable \u00b7 Dancing King Client Vault \u00b7 System Map \u00b7 v0.md",
      "sha256": "cae4d0e7503f662214d9444d7f6aafd4ce77449c0023f7486446a9b610c2d0e1",
      "size_bytes": 5710,
      "source": "airtable"
    },
    {
      "extension": ".docx",
      "json_top_level_keys": "UNKNOWN",
      "markdown_heading": "UNKNOWN",
      "path": "inputs/airtable/AirtableSchema__DancingKingClientVault__2026-02-12T14_19_55.058Z.json.docx",
      "sha256": "3d547e95d0116db1b6b7672ac3bcf71a55da025fc35ee518d5f480cff0205df3",
      "size_bytes": 45207,
      "source": "airtable"
    },
    {
      "extension": ".json",
      "json_top_level_keys": [
        "tables"
      ],
      "markdown_heading": "UNKNOWN",
      "path": "inputs/airtable/AirtableSchema__DancingKingClientVault__Latest.json",
      "sha256": "9913dd751b063d4e6c3cc3f34867d9d86a7f6d32059319d3d16bfefdd0df5598",
      "size_bytes": 173230,
      "source": "airtable"
    },
    {
      "extension": ".json",
      "json_top_level_keys": [
        "base_id",
        "fetched_at",
        "ok",
        "tables"
      ],
      "markdown_heading": "UNKNOWN",
      "path": "inputs/airtable/AirtableSchema__app0ezVqvqQRWTXIJ__Latest.json",
      "sha256": "dc7897cb0fa9403741e25b4551d16ffe2a7bfad39f145f31124abe767eb7d987",
      "size_bytes": 340628,
      "source": "airtable"
    },
    {
      "extension": ".json",
      "json_top_level_keys": [
        "base_id",
        "fetched_at",
        "ok",
        "tables"
      ],
      "markdown_heading": "UNKNOWN",
      "path": "inputs/airtable/AirtableSchema__appQFyu6Aejoq7yHP__Latest.json",
      "sha256": "5122b74caa8192fd15148fc48ddf0bb46b62cb3135909bd6c931c558dd5695da",
      "size_bytes": 7948,
      "source": "airtable"
    },
    {
      "extension": ".md",
      "json_top_level_keys": "UNKNOWN",
      "markdown_heading": "Airtable inputs",
      "path": "inputs/airtable/README.md",
      "sha256": "8c8d683fed51f38ccf728d7ed2c2c8e9a1490b8a85b689ecdcebc3bd1d04d1b0",
      "size_bytes": 320,
      "source": "airtable"
    },
    {
      "extension": ".md",
      "json_top_level_keys": "UNKNOWN",
      "markdown_heading": "Change Notes Index",
      "path": "inputs/changelog/index.md",
      "sha256": "517a5cdc1054225ba6b998291ce36ac9f712a182f2a33928902df91ee6d7c114",
      "size_bytes": 525,
      "source": "changelog"
    },
    {
      "extension": ".md",
      "json_top_level_keys": "UNKNOWN",
      "markdown_heading": "UNKNOWN",
      "path": "inputs/clay/README.md",
      "sha256": "e1412f34f8f980eab6d1033f9a55a215203a51977b62de2158a083fe7d09eafe",
      "size_bytes": 91,
      "source": "clay"
    },
    {
      "extension": ".json",
      "json_top_level_keys": [
        "calendars",
        "count",
        "fetched_at",
        "location_id",
        "ok",
        "source",
        "status"
      ],
      "markdown_heading": "UNKNOWN",
      "path": "inputs/ghl/GHLCalendars__JH4o9LqPhHyuvvyVFJVZ__Latest.json",
      "sha256": "3f4d0bbcb524c88eae49fd1ed920224d222a71f4781a50b1c411c4e5dab98660",
      "size_bytes": 78186,
      "source": "ghl"
    },
    {
      "extension": ".json",
      "json_top_level_keys": [
        "contacts",
        "count",
        "fetched_at",
        "location_id",
        "ok",
        "source",
        "status"
      ],
      "markdown_heading": "UNKNOWN",
      "path": "inputs/ghl/GHLContacts__JH4o9LqPhHyuvvyVFJVZ__Latest.json",
      "sha256": "146fb9b137cf943923fbbfbec2a646a236d18f9d6fc0a21bcfa2d1bc4c7df420",
      "size_bytes": 3876036,
      "source": "ghl"
    },
    {
      "extension": ".json",
      "json_top_level_keys": [
        "conversations",
        "count",
        "fetched_at",
        "location_id",
        "ok",
        "source",
        "status"
      ],
      "markdown_heading": "UNKNOWN",
      "path": "inputs/ghl/GHLConversations__JH4o9LqPhHyuvvyVFJVZ__Latest.json",
      "sha256": "a5afca2dbd678bd7c288523a62cd36df64632beed169d8da74b4ce90a2664c77",
      "size_bytes": 85699,
      "source": "ghl"
    },
    {
      "extension": ".json",
      "json_top_level_keys": [
        "count",
        "custom_fields",
        "fetched_at",
        "location_id",
        "ok",
        "source",
        "status"
      ],
      "markdown_heading": "UNKNOWN",
      "path": "inputs/ghl/GHLCustomFields__JH4o9LqPhHyuvvyVFJVZ__Latest.json",
      "sha256": "b8b85a1a746d5ea7dea089624eda087aefd2f02174864a7b64722b76e06622b6",
      "size_bytes": 51874,
      "source": "ghl"
    },
    {
      "extension": ".json",
      "json_top_level_keys": [
        "count",
        "custom_values",
        "fetched_at",
        "location_id",
        "ok",
        "source",
        "status"
      ],
      "markdown_heading": "UNKNOWN",
      "path": "inputs/ghl/GHLCustomValues__JH4o9LqPhHyuvvyVFJVZ__Latest.json",
      "sha256": "418e7408127b29b7a31ffe4b0e8df4a32ba47644ecfd643614792fa4a2d4f889",
      "size_bytes": 3911,
      "source": "ghl"
    },
    {
      "extension": ".json",
      "json_top_level_keys": [
        "count",
        "email_templates",
        "fetched_at",
        "location_id",
        "ok",
        "source",
        "status"
      ],
      "markdown_heading": "UNKNOWN",
      "path": "inputs/ghl/GHLEmailTemplates__JH4o9LqPhHyuvvyVFJVZ__Latest.json",
      "sha256": "c836af0536d9f40633fc8d5ec5a2dba38f52352a93ca1cddb3c3785401f76cfc",
      "size_bytes": 172,
      "source": "ghl"
    },
    {
      "extension": ".json",
      "json_top_level_keys": [
        "count",
        "fetched_at",
        "forms",
        "location_id",
        "ok",
        "source",
        "status"
      ],
      "markdown_heading": "UNKNOWN",
      "path": "inputs/ghl/GHLForms__JH4o9LqPhHyuvvyVFJVZ__Latest.json",
      "sha256": "a59c8fe3826c582d0cc441e3bc9e11f4ddf11602f4abe18018f23e6fa439d2ed",
      "size_bytes": 1371,
      "source": "ghl"
    },
    {
      "extension": ".json",
      "json_top_level_keys": [
        "count",
        "fetched_at",
        "funnels",
        "location_id",
        "ok",
        "source",
        "status"
      ],
      "markdown_heading": "UNKNOWN",
      "path": "inputs/ghl/GHLFunnels__JH4o9LqPhHyuvvyVFJVZ__Latest.json",
      "sha256": "1d456ad467729743c63fa7a2bf7d942d5c170a030e9c24b3c44c3fea1b2112b6",
      "size_bytes": 38082,
      "source": "ghl"
    },
    {
      "extension": ".json",
      "json_top_level_keys": [
        "fetched_at",
        "location",
        "location_id",
        "ok",
        "source",
        "status"
      ],
      "markdown_heading": "UNKNOWN",
      "path": "inputs/ghl/GHLLocation__JH4o9LqPhHyuvvyVFJVZ__Latest.json",
      "sha256": "1df076f3301a4a956d9d31dc489e4eeab675ae3e61c8caad40cc7245ff0acbf3",
      "size_bytes": 3665,
      "source": "ghl"
    },
    {
      "extension": ".json",
      "json_top_level_keys": [
        "count",
        "fetched_at",
        "location_id",
        "ok",
        "pipelines",
        "source",
        "status"
      ],
      "markdown_heading": "UNKNOWN",
      "path": "inputs/ghl/GHLPipelines__JH4o9LqPhHyuvvyVFJVZ__Latest.json",
      "sha256": "0c586331c2b8dd9835bbd3432e861d4c969127efeff8447dbf13276e87ade396",
      "size_bytes": 11456,
      "source": "ghl"
    },
    {
      "extension": ".json",
      "json_top_level_keys": [
        "count",
        "fetched_at",
        "location_id",
        "ok",
        "source",
        "status",
        "tags"
      ],
      "markdown_heading": "UNKNOWN",
      "path": "inputs/ghl/GHLTags__JH4o9LqPhHyuvvyVFJVZ__Latest.json",
      "sha256": "0860b3f637fe6939e49863f98617c97df27009f640314fa80b8a8f3e4563aa90",
      "size_bytes": 6357,
      "source": "ghl"
    },
    {
      "extension": ".json",
      "json_top_level_keys": [
        "error",
        "fetched_at",
        "location_id",
        "ok",
        "source",
        "status",
        "trigger_links"
      ],
      "markdown_heading": "UNKNOWN",
      "path": "inputs/ghl/GHLTriggerLinks__JH4o9LqPhHyuvvyVFJVZ__Latest.json",
      "sha256": "e24ad79354f31fd568ee5c370726da5e1b4cc85ac3cb192a1647e83fcb2af823",
      "size_bytes": 411,
      "source": "ghl"
    },
    {
      "extension": ".json",
      "json_top_level_keys": [
        "count",
        "fetched_at",
        "location_id",
        "ok",
        "source",
        "status",
        "users"
      ],
      "markdown_heading": "UNKNOWN",
      "path": "inputs/ghl/GHLUsers__JH4o9LqPhHyuvvyVFJVZ__Latest.json",
      "sha256": "65985ea827b2e5ff074208d47d1d31476cf1e33826cb85d8a10576edad95d3d7",
      "size_bytes": 11330,
      "source": "ghl"
    },
    {
      "extension": ".json",
      "json_top_level_keys": [
        "error",
        "fetched_at",
        "ok",
        "source",
        "status",
        "workflow",
        "workflow_id"
      ],
      "markdown_heading": "UNKNOWN",
      "path": "inputs/ghl/GHLWorkflow__82cb0414-c64a-4fdd-8961-96719dea3878__Latest.json",
      "sha256": "310110b731cd7d1a9f431d988dce3076d602e48232f2c0a18df7240db1b140a1",
      "size_bytes": 465,
      "source": "ghl"
    },
    {
      "extension": ".json",
      "json_top_level_keys": [
        "error",
        "fetched_at",
        "ok",
        "source",
        "status",
        "workflow",
        "workflow_id"
      ],
      "markdown_heading": "UNKNOWN",
      "path": "inputs/ghl/GHLWorkflow__90cecd4e-e701-46bb-87c5-9aa43c2b0ea5__Latest.json",
      "sha256": "5129897f17b0d95e691c9555f2ae7e5bfa3339a68e88e8886d1f3b6885312a51",
      "size_bytes": 465,
      "source": "ghl"
    },
    {
      "extension": ".json",
      "json_top_level_keys": [
        "count",
        "fetched_at",
        "location_id",
        "ok",
        "source",
        "status",
        "workflows"
      ],
      "markdown_heading": "UNKNOWN",
      "path": "inputs/ghl/GHLWorkflows__JH4o9LqPhHyuvvyVFJVZ__Latest.json",
      "sha256": "b1f58100b04fa986a872b4122fddfa0b0eef984e64a369d80a59f354f28ef07b",
      "size_bytes": 11625,
      "source": "ghl"
    },
    {
      "extension": ".md",
      "json_top_level_keys": "UNKNOWN",
      "markdown_heading": "GHL inputs",
      "path": "inputs/ghl/README.md",
      "sha256": "fc4648180e38122827eb213adabc06bf4eb5bf1eec82358c10088e4ffcf75d4e",
      "size_bytes": 2749,
      "source": "ghl"
    },
    {
      "extension": ".json",
      "json_top_level_keys": [
        "scenario_ids"
      ],
      "markdown_heading": "UNKNOWN",
      "path": "inputs/make/MAKE_SCENARIOS.json",
      "sha256": "9ff94a0d4a7cf7e3c350b91993842be6a41e3dcfc3d0e7ac2e2b19930d2c73e5",
      "size_bytes": 162,
      "source": "make"
    },
    {
      "extension": ".json",
      "json_top_level_keys": [
        "base_url",
        "count",
        "fetched_at",
        "organization_id",
        "scenario_source",
        "scenarios",
        "team_id"
      ],
      "markdown_heading": "UNKNOWN",
      "path": "inputs/make/MAKE_SCENARIO_INDEX__Latest.json",
      "sha256": "56ea785260cbc039a82f62f7519d1180febdb63676e3bdd6974f0df2239cd551",
      "size_bytes": 5508,
      "source": "make"
    },
    {
      "extension": ".json",
      "json_top_level_keys": [
        "fetched_at",
        "ok",
        "organization_id",
        "raw",
        "scenarios",
        "status",
        "team_id"
      ],
      "markdown_heading": "UNKNOWN",
      "path": "inputs/make/MAKE_SCENARIO_LISTING__Latest.json",
      "sha256": "542dcbbf404fdcc3d266d8ddd9f82013a4ff1905a7b0b85747c29700b17f065d",
      "size_bytes": 113052,
      "source": "make"
    },
    {
      "extension": ".json",
      "json_top_level_keys": [
        "base_url",
        "count",
        "fetched_at",
        "organization_id",
        "scenario_source",
        "scenarios",
        "team_id"
      ],
      "markdown_heading": "UNKNOWN",
      "path": "inputs/make/MakeProbe__Latest.json",
      "sha256": "48a0284dd76692f528fd11af6d84dba0c1446f3964aa99eeab5a2ab8ffd3cb6e",
      "size_bytes": 6831,
      "source": "make"
    },
    {
      "extension": ".md",
      "json_top_level_keys": "UNKNOWN",
      "markdown_heading": "Make inputs",
      "path": "inputs/make/README.md",
      "sha256": "bd15888f70af735fc7f74527db150d07b210fef7bdfeb9870eb21cf7c3675169",
      "size_bytes": 575,
      "source": "make"
    },
    {
      "extension": ".json",
      "json_top_level_keys": [
        "fetched_at",
        "response",
        "scenario_id",
        "status"
      ],
      "markdown_heading": "UNKNOWN",
      "path": "inputs/make/blueprints/MakeBlueprint__2348337__Latest.json",
      "sha256": "03689ef517e0fd79fb64a43444d9d3e8640017144606d5f5563a491d37c3a41b",
      "size_bytes": 29039,
      "source": "make"
    },
    {
      "extension": ".json",
      "json_top_level_keys": [
        "fetched_at",
        "response",
        "scenario_id",
        "status"
      ],
      "markdown_heading": "UNKNOWN",
      "path": "inputs/make/blueprints/MakeBlueprint__3664392__Latest.json",
      "sha256": "4123c7d4e9ff09cf8e7613d4b8ae38933e5c82a1d4feba59105ea595554f850a",
      "size_bytes": 133837,
      "source": "make"
    },
    {
      "extension": ".json",
      "json_top_level_keys": [
        "fetched_at",
        "response",
        "scenario_id",
        "status"
      ],
      "markdown_heading": "UNKNOWN",
      "path": "inputs/make/blueprints/MakeBlueprint__3673026__Latest.json",
      "sha256": "c9fc06f326c69d30e0e6dc6e1cbd4cc89792307124dccbad14eb0289773f0979",
      "size_bytes": 193486,
      "source": "make"
    },
    {
      "extension": ".json",
      "json_top_level_keys": [
        "fetched_at",
        "response",
        "scenario_id",
        "status"
      ],
      "markdown_heading": "UNKNOWN",
      "path": "inputs/make/blueprints/MakeBlueprint__3686763__Latest.json",
      "sha256": "c9ab379d05f08d3964939677039c53e16ee10bee78c82034840f65a0eabe6d13",
      "size_bytes": 132491,
      "source": "make"
    },
    {
      "extension": ".json",
      "json_top_level_keys": [
        "fetched_at",
        "response",
        "scenario_id",
        "status"
      ],
      "markdown_heading": "UNKNOWN",
      "path": "inputs/make/blueprints/MakeBlueprint__3686991__Latest.json",
      "sha256": "0fe27732ad350e6e85a24b641c43a9e8c432cfd1f793102d17057641df34e799",
      "size_bytes": 138096,
      "source": "make"
    },
    {
      "extension": ".json",
      "json_top_level_keys": [
        "fetched_at",
        "response",
        "scenario_id",
        "status"
      ],
      "markdown_heading": "UNKNOWN",
      "path": "inputs/make/blueprints/MakeBlueprint__3687011__Latest.json",
      "sha256": "12e5e599c06c0ace046d365b5772400a7eb1a3bcb7e62b415237a323025d6348",
      "size_bytes": 87666,
      "source": "make"
    },
    {
      "extension": ".json",
      "json_top_level_keys": [
        "fetched_at",
        "response",
        "scenario_id",
        "status"
      ],
      "markdown_heading": "UNKNOWN",
      "path": "inputs/make/blueprints/MakeBlueprint__3733465__Latest.json",
      "sha256": "af646bc8b50c8c7e7743e822ce1aa39dded77c816177b3a857d670fb3c3fe765",
      "size_bytes": 571925,
      "source": "make"
    },
    {
      "extension": ".json",
      "json_top_level_keys": [
        "fetched_at",
        "response",
        "scenario_id",
        "status"
      ],
      "markdown_heading": "UNKNOWN",
      "path": "inputs/make/blueprints/MakeBlueprint__3738189__Latest.json",
      "sha256": "ca9be3f734ada280dcb8ba6b32fa38e27315395b24b14a34559cafb82bd3d65e",
      "size_bytes": 146399,
      "source": "make"
    },
    {
      "extension": ".json",
      "json_top_level_keys": [
        "fetched_at",
        "response",
        "scenario_id",
        "status"
      ],
      "markdown_heading": "UNKNOWN",
      "path": "inputs/make/blueprints/MakeBlueprint__3744510__Latest.json",
      "sha256": "2518aa7634491d66d3234ef7f11eead2870dbc5e0b693a2e453dd1ad244bbb8d",
      "size_bytes": 338031,
      "source": "make"
    },
    {
      "extension": ".json",
      "json_top_level_keys": [
        "fetched_at",
        "response",
        "scenario_id",
        "status"
      ],
      "markdown_heading": "UNKNOWN",
      "path": "inputs/make/blueprints/MakeBlueprint__3745933__Latest.json",
      "sha256": "0609b8306d88b7eecb1ca2d785a9a0553c41c59aac531a7bc496d6675434657d",
      "size_bytes": 124315,
      "source": "make"
    },
    {
      "extension": ".json",
      "json_top_level_keys": [
        "fetched_at",
        "response",
        "scenario_id",
        "status"
      ],
      "markdown_heading": "UNKNOWN",
      "path": "inputs/make/blueprints/MakeBlueprint__3761572__Latest.json",
      "sha256": "57a8306d38db74a26faa49fcc26c5b79d4166500fbd7d17d58237b3e13183cac",
      "size_bytes": 230606,
      "source": "make"
    },
    {
      "extension": ".json",
      "json_top_level_keys": [
        "fetched_at",
        "response",
        "scenario_id",
        "status"
      ],
      "markdown_heading": "UNKNOWN",
      "path": "inputs/make/blueprints/MakeBlueprint__3795815__Latest.json",
      "sha256": "52529b26b47b9b05ed2a3153989f0aa1b526a8e9051fd9419afc0e883409a6db",
      "size_bytes": 211984,
      "source": "make"
    },
    {
      "extension": ".json",
      "json_top_level_keys": [
        "fetched_at",
        "response",
        "scenario_id",
        "status"
      ],
      "markdown_heading": "UNKNOWN",
      "path": "inputs/make/blueprints/MakeBlueprint__3798600__Latest.json",
      "sha256": "a6fa4477984be800ddc50da63b1f13b5f7cfa83a4a8e1fdc8b95e739e766d4d5",
      "size_bytes": 300381,
      "source": "make"
    },
    {
      "extension": ".json",
      "json_top_level_keys": [
        "fetched_at",
        "response",
        "scenario_id",
        "status"
      ],
      "markdown_heading": "UNKNOWN",
      "path": "inputs/make/blueprints/MakeBlueprint__3818644__Latest.json",
      "sha256": "98851b1cc7e87cb988d131c5955c6ca3a34b375437fb48f479a47dec69382bcf",
      "size_bytes": 195490,
      "source": "make"
    },
    {
      "extension": ".json",
      "json_top_level_keys": [
        "fetched_at",
        "response",
        "scenario_id",
        "status"
      ],
      "markdown_heading": "UNKNOWN",
      "path": "inputs/make/blueprints/MakeBlueprint__3818650__Latest.json",
      "sha256": "44c7025d893b21510216023fa6ed22a40ca58101f49bde8e9926ae382439b396",
      "size_bytes": 188936,
      "source": "make"
    },
    {
      "extension": ".json",
      "json_top_level_keys": [
        "fetched_at",
        "response",
        "scenario_id",
        "status"
      ],
      "markdown_heading": "UNKNOWN",
      "path": "inputs/make/blueprints/MakeBlueprint__3818652__Latest.json",
      "sha256": "6229be1749a4af1157d2225de9c86e639d076468e57bb1439302155fbece4389",
      "size_bytes": 214238,
      "source": "make"
    },
    {
      "extension": ".json",
      "json_top_level_keys": [
        "fetched_at",
        "response",
        "scenario_id",
        "status"
      ],
      "markdown_heading": "UNKNOWN",
      "path": "inputs/make/blueprints/MakeBlueprint__3818663__Latest.json",
      "sha256": "540688b0d2707293bdbf61c6117608ea19120aa4d3d862607dba1bcf9999d3d4",
      "size_bytes": 198409,
      "source": "make"
    },
    {
      "extension": ".json",
      "json_top_level_keys": [
        "fetched_at",
        "response",
        "scenario_id",
        "status"
      ],
      "markdown_heading": "UNKNOWN",
      "path": "inputs/make/blueprints/MakeBlueprint__3824254__Latest.json",
      "sha256": "4829b1a5fa632f52de9f47fcd743e276747f6a80fac2302a4b265475c1f5ac70",
      "size_bytes": 498670,
      "source": "make"
    },
    {
      "extension": ".json",
      "json_top_level_keys": [
        "fetched_at",
        "response",
        "scenario_id",
        "status"
      ],
      "markdown_heading": "UNKNOWN",
      "path": "inputs/make/blueprints/MakeBlueprint__3824833__Latest.json",
      "sha256": "5b31aa89d867266a6278cf705b86418d2e61c8807716328775468a8027e6f61b",
      "size_bytes": 214975,
      "source": "make"
    },
    {
      "extension": ".json",
      "json_top_level_keys": [
        "fetched_at",
        "response",
        "scenario_id",
        "status"
      ],
      "markdown_heading": "UNKNOWN",
      "path": "inputs/make/blueprints/MakeBlueprint__3859876__Latest.json",
      "sha256": "863daf3c86ded986fd78e2c7fbfdbfb2171da799f5ab4f2d0f3b81693164060e",
      "size_bytes": 3320532,
      "source": "make"
    },
    {
      "extension": ".json",
      "json_top_level_keys": [
        "fetched_at",
        "response",
        "scenario_id",
        "status"
      ],
      "markdown_heading": "UNKNOWN",
      "path": "inputs/make/blueprints/MakeBlueprint__3920516__Latest.json",
      "sha256": "4672cb2905c054d08e308907b3dff6b90a68bf5f5a627122ac65763a64830d23",
      "size_bytes": 211170,
      "source": "make"
    },
    {
      "extension": ".json",
      "json_top_level_keys": [
        "fetched_at",
        "response",
        "scenario_id",
        "status"
      ],
      "markdown_heading": "UNKNOWN",
      "path": "inputs/make/blueprints/MakeBlueprint__3920818__Latest.json",
      "sha256": "ef58b015b2cd864dc921f8817ccadf5bf310208ff353e3bd671afcd94369c4d8",
      "size_bytes": 226847,
      "source": "make"
    },
    {
      "extension": ".json",
      "json_top_level_keys": [
        "fetched_at",
        "response",
        "scenario_id",
        "status"
      ],
      "markdown_heading": "UNKNOWN",
      "path": "inputs/make/blueprints/MakeBlueprint__3952284__Latest.json",
      "sha256": "4911453e8d157e80a8982d128863ff51ac165ef9bef113e7f1a3eee9ed86c82a",
      "size_bytes": 298372,
      "source": "make"
    },
    {
      "extension": ".json",
      "json_top_level_keys": [
        "fetched_at",
        "response",
        "scenario_id",
        "status"
      ],
      "markdown_heading": "UNKNOWN",
      "path": "inputs/make/blueprints/MakeBlueprint__3961170__Latest.json",
      "sha256": "d5dc4351aeb06797f452f7ec099f22583508983930aa83128bf399c1bc8659fd",
      "size_bytes": 571916,
      "source": "make"
    },
    {
      "extension": ".json",
      "json_top_level_keys": [
        "fetched_at",
        "response",
        "scenario_id",
        "status"
      ],
      "markdown_heading": "UNKNOWN",
      "path": "inputs/make/blueprints/MakeBlueprint__3996198__Latest.json",
      "sha256": "c745cc1acff0f8dd9b31a37d3a793384bf5abe13fb00a15dbda3b8d7d8d2c361",
      "size_bytes": 25316,
      "source": "make"
    },
    {
      "extension": ".json",
      "json_top_level_keys": [
        "fetched_at",
        "response",
        "scenario_id",
        "status"
      ],
      "markdown_heading": "UNKNOWN",
      "path": "inputs/make/blueprints/MakeBlueprint__4001823__Latest.json",
      "sha256": "1215c44e1a8e7f0a5ed31c4b69eccb47e85c1b71209dbe356b794b4939c04ba1",
      "size_bytes": 39815,
      "source": "make"
    },
    {
      "extension": ".json",
      "json_top_level_keys": [
        "fetched_at",
        "response",
        "scenario_id",
        "status"
      ],
      "markdown_heading": "UNKNOWN",
      "path": "inputs/make/blueprints/MakeBlueprint__4002164__Latest.json",
      "sha256": "5d187d5abce2cbb139463de65401221b14f9b0c948d6109ceabca2eca12145d4",
      "size_bytes": 32336,
      "source": "make"
    },
    {
      "extension": ".json",
      "json_top_level_keys": [
        "fetched_at",
        "response",
        "scenario_id",
        "status"
      ],
      "markdown_heading": "UNKNOWN",
      "path": "inputs/make/blueprints/MakeBlueprint__4002272__Latest.json",
      "sha256": "b8cca34fa49469a3793b8f8c4bcdde1a1748786969f51c109e301ba416b013a8",
      "size_bytes": 28557,
      "source": "make"
    },
    {
      "extension": ".json",
      "json_top_level_keys": [
        "fetched_at",
        "response",
        "scenario_id",
        "status"
      ],
      "markdown_heading": "UNKNOWN",
      "path": "inputs/make/blueprints/MakeBlueprint__4055279__Latest.json",
      "sha256": "8d960d98c59c631b6f097b24f6061a717b1ec8ad841d65b0dd652e28a8b3e4e2",
      "size_bytes": 226864,
      "source": "make"
    },
    {
      "extension": ".json",
      "json_top_level_keys": [
        "fetched_at",
        "response",
        "scenario_id",
        "status"
      ],
      "markdown_heading": "UNKNOWN",
      "path": "inputs/make/blueprints/MakeBlueprint__4055283__Latest.json",
      "sha256": "66da93d3a7c99c9d38aec74741e91d0426d972fabc8dead697aa9b9ede00d5b6",
      "size_bytes": 221165,
      "source": "make"
    },
    {
      "extension": ".json",
      "json_top_level_keys": [
        "fetched_at",
        "response",
        "scenario_id",
        "status"
      ],
      "markdown_heading": "UNKNOWN",
      "path": "inputs/make/blueprints/MakeBlueprint__4091455__Latest.json",
      "sha256": "e37c5f13ba61b3ac3c635a9bb19058032beec14dfa67c88d313829e82bb58ac6",
      "size_bytes": 998939,
      "source": "make"
    },
    {
      "extension": ".json",
      "json_top_level_keys": [
        "fetched_at",
        "response",
        "scenario_id",
        "status"
      ],
      "markdown_heading": "UNKNOWN",
      "path": "inputs/make/blueprints/MakeBlueprint__4091456__Latest.json",
      "sha256": "66f491c796b9896cbc216f4f05d405c6e81624777e6c2fe56f0b163748a9e760",
      "size_bytes": 211991,
      "source": "make"
    },
    {
      "extension": ".json",
      "json_top_level_keys": [
        "fetched_at",
        "response",
        "scenario_id",
        "status"
      ],
      "markdown_heading": "UNKNOWN",
      "path": "inputs/make/blueprints/MakeBlueprint__4093385__Latest.json",
      "sha256": "79c4eedd262620fd4dc6ea19335d2f4b3582cf92ed2cd25151924ce1dc6bf1b5",
      "size_bytes": 822256,
      "source": "make"
    },
    {
      "extension": ".json",
      "json_top_level_keys": [
        "fetched_at",
        "response",
        "scenario_id",
        "status"
      ],
      "markdown_heading": "UNKNOWN",
      "path": "inputs/make/blueprints/MakeBlueprint__4121916__Latest.json",
      "sha256": "727a57c2b3861a4186331964241122e24da75524063b5d3bdbe0da209851dd02",
      "size_bytes": 25496,
      "source": "make"
    },
    {
      "extension": ".json",
      "json_top_level_keys": [
        "fetched_at",
        "response",
        "scenario_id",
        "status"
      ],
      "markdown_heading": "UNKNOWN",
      "path": "inputs/make/blueprints/MakeBlueprint__4123962__Latest.json",
      "sha256": "8cb9b79f529886c92d5c1af30c89c256bead6c57af7fb29ac96dff574b8b0604",
      "size_bytes": 20567,
      "source": "make"
    },
    {
      "extension": ".json",
      "json_top_level_keys": [
        "fetched_at",
        "response",
        "scenario_id",
        "status"
      ],
      "markdown_heading": "UNKNOWN",
      "path": "inputs/make/blueprints/MakeBlueprint__4124710__Latest.json",
      "sha256": "fd1891e0f575a585bdb16ffda9aa02ca512d36f3c44ccc59c4ff76a0d8970383",
      "size_bytes": 23818,
      "source": "make"
    },
    {
      "extension": ".json",
      "json_top_level_keys": [
        "fetched_at",
        "response",
        "scenario_id",
        "status"
      ],
      "markdown_heading": "UNKNOWN",
      "path": "inputs/make/blueprints/MakeBlueprint__4127837__Latest.json",
      "sha256": "c5360f792750aacdfbdbc4c37eb97315ee49df6051593e109ed48b623abaef31",
      "size_bytes": 17022,
      "source": "make"
    },
    {
      "extension": ".json",
      "json_top_level_keys": [
        "fetched_at",
        "response",
        "scenario_id",
        "status"
      ],
      "markdown_heading": "UNKNOWN",
      "path": "inputs/make/blueprints/MakeBlueprint__4128249__Latest.json",
      "sha256": "7451e62f6513547a72e72fd4c0a944d24f2b3c4ba25a97c1edb40c8c094159f1",
      "size_bytes": 16293,
      "source": "make"
    },
    {
      "extension": ".json",
      "json_top_level_keys": [
        "fetched_at",
        "response",
        "scenario_id",
        "status"
      ],
      "markdown_heading": "UNKNOWN",
      "path": "inputs/make/blueprints/MakeBlueprint__4128593__Latest.json",
      "sha256": "9919ec19020038ea61bd8320a4e849bb9f41a7509f5809d215f580b008067c5f",
      "size_bytes": 12783,
      "source": "make"
    },
    {
      "extension": ".json",
      "json_top_level_keys": [
        "fetched_at",
        "response",
        "scenario_id",
        "status"
      ],
      "markdown_heading": "UNKNOWN",
      "path": "inputs/make/blueprints/MakeBlueprint__4148204__Latest.json",
      "sha256": "c393a206020fef9a3e66d8a97ff8a55c564067ba4bf4ec17ed09da3d88747ede",
      "size_bytes": 217379,
      "source": "make"
    },
    {
      "extension": ".json",
      "json_top_level_keys": [
        "fetched_at",
        "response",
        "scenario_id",
        "status"
      ],
      "markdown_heading": "UNKNOWN",
      "path": "inputs/make/blueprints/MakeBlueprint__4185478__Latest.json",
      "sha256": "d5234e28e9a940bab86f5f4abaa26413e54812c9255e0fd59e7c910ef15c72b9",
      "size_bytes": 1436544,
      "source": "make"
    },
    {
      "extension": ".json",
      "json_top_level_keys": [
        "fetched_at",
        "response",
        "scenario_id",
        "status"
      ],
      "markdown_heading": "UNKNOWN",
      "path": "inputs/make/blueprints/MakeBlueprint__4206316__Latest.json",
      "sha256": "7446c4e9e44cbb3266fdb390825829b013b0f03eb6c2b3e97f08b7b1f0bd7498",
      "size_bytes": 26384,
      "source": "make"
    },
    {
      "extension": ".json",
      "json_top_level_keys": [
        "fetched_at",
        "response",
        "scenario_id",
        "status"
      ],
      "markdown_heading": "UNKNOWN",
      "path": "inputs/make/blueprints/MakeBlueprint__4207345__Latest.json",
      "sha256": "5fe4f0574831fce5f1d7f4e61efa319d63b2921f91fb9f867d0504da614422c7",
      "size_bytes": 12419,
      "source": "make"
    },
    {
      "extension": ".json",
      "json_top_level_keys": [
        "fetched_at",
        "response",
        "scenario_id",
        "status"
      ],
      "markdown_heading": "UNKNOWN",
      "path": "inputs/make/blueprints/MakeBlueprint__4226576__Latest.json",
      "sha256": "b422ec942eb1bb9fdea198ce320e45911e5b82bbffb5540a966498facbdf47a2",
      "size_bytes": 164075,
      "source": "make"
    },
    {
      "extension": ".json",
      "json_top_level_keys": [
        "fetched_at",
        "response",
        "scenario_id",
        "status"
      ],
      "markdown_heading": "UNKNOWN",
      "path": "inputs/make/blueprints/MakeBlueprint__4227392__Latest.json",
      "sha256": "bf00114869ae166045311029e305f3852523316183dfb314aa855d5025e61a4c",
      "size_bytes": 97502,
      "source": "make"
    },
    {
      "extension": ".json",
      "json_top_level_keys": [
        "fetched_at",
        "response",
        "scenario_id",
        "status"
      ],
      "markdown_heading": "UNKNOWN",
      "path": "inputs/make/blueprints/MakeBlueprint__4265554__Latest.json",
      "sha256": "186c5d7387a0df030031a6d74f261247b1f424d28e77258699ee081c509e303e",
      "size_bytes": 714798,
      "source": "make"
    },
    {
      "extension": ".json",
      "json_top_level_keys": [
        "fetched_at",
        "response",
        "scenario_id",
        "status"
      ],
      "markdown_heading": "UNKNOWN",
      "path": "inputs/make/blueprints/MakeBlueprint__4267051__Latest.json",
      "sha256": "616c77ead0c5ec9c8930b7fb21914eca3e23c8f068401af816700b290f454d25",
      "size_bytes": 964274,
      "source": "make"
    },
    {
      "extension": ".json",
      "json_top_level_keys": [
        "fetched_at",
        "response",
        "scenario_id",
        "status"
      ],
      "markdown_heading": "UNKNOWN",
      "path": "inputs/make/blueprints/MakeBlueprint__4267120__Latest.json",
      "sha256": "990711faa9ac553f848f6a49cb3438eab62967124f0b3fc7de1fb36ed9d78369",
      "size_bytes": 82247,
      "source": "make"
    },
    {
      "extension": ".json",
      "json_top_level_keys": [
        "fetched_at",
        "response",
        "scenario_id",
        "status"
      ],
      "markdown_heading": "UNKNOWN",
      "path": "inputs/make/blueprints/MakeBlueprint__4328562__Latest.json",
      "sha256": "fc3b8ff55bc0ebe319b86b092542a2195d36c0fd8a15e9e9dc37f3ab23e8a487",
      "size_bytes": 16101,
      "source": "make"
    },
    {
      "extension": ".json",
      "json_top_level_keys": [
        "fetched_at",
        "response",
        "scenario_id",
        "status"
      ],
      "markdown_heading": "UNKNOWN",
      "path": "inputs/make/blueprints/MakeBlueprint__4347798__Latest.json",
      "sha256": "e7f09d04f6d04191439f5b1c867ea6e02ddf4c1fd154c77f5ae556c484017820",
      "size_bytes": 1029901,
      "source": "make"
    },
    {
      "extension": ".json",
      "json_top_level_keys": [
        "fetched_at",
        "response",
        "scenario_id",
        "status"
      ],
      "markdown_heading": "UNKNOWN",
      "path": "inputs/make/blueprints/MakeBlueprint__4360004__Latest.json",
      "sha256": "284feb7a560a65e16c3f17f12c812b025c51038df72be9e83248bc8c3dc75a49",
      "size_bytes": 1046362,
      "source": "make"
    },
    {
      "extension": ".md",
      "json_top_level_keys": "UNKNOWN",
      "markdown_heading": "UNKNOWN",
      "path": "inputs/make/blueprints/README.md",
      "sha256": "01ba4719c80b6fe911b091a7c05124b64eeece964e09c058ef8f9805daca546b",
      "size_bytes": 1,
      "source": "make"
    },
    {
      "extension": ".md",
      "json_top_level_keys": "UNKNOWN",
      "markdown_heading": "**C12 Intel Report \u2013 Scenario Digest**",
      "path": "inputs/make/digests/MakeDigest__C12IntelReportDigest__3798600__v0.1.json.md",
      "sha256": "20d070c17715a79f76e8e70250313c5a84d7d093676800babe0330abe75d7248",
      "size_bytes": 10566,
      "source": "make"
    },
    {
      "extension": ".md",
      "json_top_level_keys": "UNKNOWN",
      "markdown_heading": "**1\\. Scenario Overview**",
      "path": "inputs/make/digests/MakeDigest__EmailConveyor__4093385__2026-02-12T15-09-37.json.md",
      "sha256": "e90aa6df102bf254902c60ce550c539d26e2ac5cc475d43d61d9c0c821ac8803",
      "size_bytes": 12100,
      "source": "make"
    },
    {
      "extension": ".md",
      "json_top_level_keys": "UNKNOWN",
      "markdown_heading": "**1\\. Scenario Overview**",
      "path": "inputs/make/digests/MakeDigest__IntelConveyor__4091455__v0.1.json.md",
      "sha256": "53a77d65c43a715a2698931f84cba84658529ab52d75a399c758245b5d6c7d76",
      "size_bytes": 14971,
      "source": "make"
    },
    {
      "extension": ".md",
      "json_top_level_keys": "UNKNOWN",
      "markdown_heading": "UNKNOWN",
      "path": "inputs/make/digests/README.md",
      "sha256": "01ba4719c80b6fe911b091a7c05124b64eeece964e09c058ef8f9805daca546b",
      "size_bytes": 1,
      "source": "make"
    },
    {
      "extension": ".md",
      "json_top_level_keys": "UNKNOWN",
      "markdown_heading": "System Model Index",
      "path": "inputs/models/system/index.md",
      "sha256": "215a32cbe77d5ae84e6c7deac090b17d4895902a8cff6a4a0e26ff33b9ef6ab6",
      "size_bytes": 623,
      "source": "models"
    },
    {
      "extension": ".md",
      "json_top_level_keys": "UNKNOWN",
      "markdown_heading": "UNKNOWN",
      "path": "inputs/qb/QB Centurion Intel SEED (1).md",
      "sha256": "42562596853325b26e87daf7d81b090ca2523952fc75bc22c46ab6ee5b329917",
      "size_bytes": 12159,
      "source": "qb"
    },
    {
      "extension": ".md",
      "json_top_level_keys": "UNKNOWN",
      "markdown_heading": "**QB\\_\\_CenturionIntel\\_\\_v0.3**",
      "path": "inputs/qb/QB__CenturionIntel__v0.3.md",
      "sha256": "4d3e18a9432cf30e6f5cdda7cb91e8caa52dcc7533f54dce62010d871eb5023e",
      "size_bytes": 29010,
      "source": "qb"
    },
    {
      "extension": ".md",
      "json_top_level_keys": "UNKNOWN",
      "markdown_heading": "UNKNOWN",
      "path": "inputs/qb/README.md",
      "sha256": "01ba4719c80b6fe911b091a7c05124b64eeece964e09c058ef8f9805daca546b",
      "size_bytes": 1,
      "source": "qb"
    },
    {
      "extension": ".md",
      "json_top_level_keys": "UNKNOWN",
      "markdown_heading": "Snapshot Index",
      "path": "inputs/snapshots/index.md",
      "sha256": "bcdc19bcd1f39d6fb372d519e0f8b31ae845dfa9ddee87aae7fa15862801b21c",
      "size_bytes": 783,
      "source": "snapshots"
    },
    {
      "extension": ".md",
      "json_top_level_keys": "UNKNOWN",
      "markdown_heading": "Softr inputs",
      "path": "inputs/softr/README.md",
      "sha256": "2ec04e8d4f3221fb2b967f16e33bbd543e09552a9199d00b6c9237320844a4b4",
      "size_bytes": 371,
      "source": "softr"
    },
    {
      "extension": ".json",
      "json_top_level_keys": [
        "count",
        "fetched_at",
        "ok",
        "source",
        "status",
        "users"
      ],
      "markdown_heading": "UNKNOWN",
      "path": "inputs/softr/SoftrUsers__Latest.json",
      "sha256": "a260f8fb1e70214142c518642a6c23272d9070144376b35141bdb42bd8d457b3",
      "size_bytes": 123,
      "source": "softr"
    },
    {
      "extension": ".md",
      "json_top_level_keys": "UNKNOWN",
      "markdown_heading": "VideoAsk inputs",
      "path": "inputs/videoask/README.md",
      "sha256": "58ed9d7c5deb084021349511eed0b933614ad32a7767ae3a5883691354a49e11",
      "size_bytes": 418,
      "source": "videoask"
    },
    {
      "extension": ".json",
      "json_top_level_keys": [
        "count",
        "fetched_at",
        "forms",
        "ok",
        "source",
        "status"
      ],
      "markdown_heading": "UNKNOWN",
      "path": "inputs/videoask/VideoAskForms__Latest.json",
      "sha256": "7a1bcf9d0a4111c13b17af794965fd54188b32e0f90001720299773b5d1ad29c",
      "size_bytes": 55381,
      "source": "videoask"
    },
    {
      "extension": ".md",
      "json_top_level_keys": "UNKNOWN",
      "markdown_heading": "UNKNOWN",
      "path": "inputs/videopeel/readme.md",
      "sha256": "01ba4719c80b6fe911b091a7c05124b64eeece964e09c058ef8f9805daca546b",
      "size_bytes": 1,
      "source": "videopeel"
    },
    {
      "extension": ".md",
      "json_top_level_keys": "UNKNOWN",
      "markdown_heading": "UNKNOWN",
      "path": "inputs/web/readme.md",
      "sha256": "01ba4719c80b6fe911b091a7c05124b64eeece964e09c058ef8f9805daca546b",
      "size_bytes": 1,
      "source": "web"
    }
  ],
  "inferred_system_structure": "UNKNOWN",
  "inputs_root": "inputs",
  "nodes": [
    {
      "id": "atlas",
      "kind": "atlas",
      "label": "Centurion Intel Atlas"
    },
    {
      "id": "source:airtable",
      "kind": "source",
      "label": "airtable"
    },
    {
      "id": "source:changelog",
      "kind": "source",
      "label": "changelog"
    },
    {
      "id": "source:clay",
      "kind": "source",
      "label": "clay"
    },
    {
      "id": "source:ghl",
      "kind": "source",
      "label": "ghl"
    },
    {
      "id": "source:make",
      "kind": "source",
      "label": "make"
    },
    {
      "id": "source:models",
      "kind": "source",
      "label": "models"
    },
    {
      "id": "source:qb",
      "kind": "source",
      "label": "qb"
    },
    {
      "id": "source:root",
      "kind": "source",
      "label": "root"
    },
    {
      "id": "source:snapshots",
      "kind": "source",
      "label": "snapshots"
    },
    {
      "id": "source:softr",
      "kind": "source",
      "label": "softr"
    },
    {
      "id": "source:videoask",
      "kind": "source",
      "label": "videoask"
    },
    {
      "id": "source:videopeel",
      "kind": "source",
      "label": "videopeel"
    },
    {
      "id": "source:web",
      "kind": "source",
      "label": "web"
    },
    {
      "extension": ".md",
      "id": "file:inputs/README.md",
      "kind": "file",
      "label": "inputs/README.md",
      "source": "root"
    },
    {
      "extension": ".md",
      "id": "file:inputs/airtable/Airtable \u00b7 Dancing King Client Vault \u00b7 System Map \u00b7 v0.md",
      "kind": "file",
      "label": "inputs/airtable/Airtable \u00b7 Dancing King Client Vault \u00b7 System Map \u00b7 v0.md",
      "source": "airtable"
    },
    {
      "extension": ".docx",
      "id": "file:inputs/airtable/AirtableSchema__DancingKingClientVault__2026-02-12T14_19_55.058Z.json.docx",
      "kind": "file",
      "label": "inputs/airtable/AirtableSchema__DancingKingClientVault__2026-02-12T14_19_55.058Z.json.docx",
      "source": "airtable"
    },
    {
      "extension": ".json",
      "id": "file:inputs/airtable/AirtableSchema__DancingKingClientVault__Latest.json",
      "kind": "file",
      "label": "inputs/airtable/AirtableSchema__DancingKingClientVault__Latest.json",
      "source": "airtable"
    },
    {
      "extension": ".json",
      "id": "file:inputs/airtable/AirtableSchema__app0ezVqvqQRWTXIJ__Latest.json",
      "kind": "file",
      "label": "inputs/airtable/AirtableSchema__app0ezVqvqQRWTXIJ__Latest.json",
      "source": "airtable"
    },
    {
      "extension": ".json",
      "id": "file:inputs/airtable/AirtableSchema__appQFyu6Aejoq7yHP__Latest.json",
      "kind": "file",
      "label": "inputs/airtable/AirtableSchema__appQFyu6Aejoq7yHP__Latest.json",
      "source": "airtable"
    },
    {
      "extension": ".md",
      "id": "file:inputs/airtable/README.md",
      "kind": "file",
      "label": "inputs/airtable/README.md",
      "source": "airtable"
    },
    {
      "extension": ".md",
      "id": "file:inputs/changelog/index.md",
      "kind": "file",
      "label": "inputs/changelog/index.md",
      "source": "changelog"
    },
    {
      "extension": ".md",
      "id": "file:inputs/clay/README.md",
      "kind": "file",
      "label": "inputs/clay/README.md",
      "source": "clay"
    },
    {
      "extension": ".json",
      "id": "file:inputs/ghl/GHLCalendars__JH4o9LqPhHyuvvyVFJVZ__Latest.json",
      "kind": "file",
      "label": "inputs/ghl/GHLCalendars__JH4o9LqPhHyuvvyVFJVZ__Latest.json",
      "source": "ghl"
    },
    {
      "extension": ".json",
      "id": "file:inputs/ghl/GHLContacts__JH4o9LqPhHyuvvyVFJVZ__Latest.json",
      "kind": "file",
      "label": "inputs/ghl/GHLContacts__JH4o9LqPhHyuvvyVFJVZ__Latest.json",
      "source": "ghl"
    },
    {
      "extension": ".json",
      "id": "file:inputs/ghl/GHLConversations__JH4o9LqPhHyuvvyVFJVZ__Latest.json",
      "kind": "file",
      "label": "inputs/ghl/GHLConversations__JH4o9LqPhHyuvvyVFJVZ__Latest.json",
      "source": "ghl"
    },
    {
      "extension": ".json",
      "id": "file:inputs/ghl/GHLCustomFields__JH4o9LqPhHyuvvyVFJVZ__Latest.json",
      "kind": "file",
      "label": "inputs/ghl/GHLCustomFields__JH4o9LqPhHyuvvyVFJVZ__Latest.json",
      "source": "ghl"
    },
    {
      "extension": ".json",
      "id": "file:inputs/ghl/GHLCustomValues__JH4o9LqPhHyuvvyVFJVZ__Latest.json",
      "kind": "file",
      "label": "inputs/ghl/GHLCustomValues__JH4o9LqPhHyuvvyVFJVZ__Latest.json",
      "source": "ghl"
    },
    {
      "extension": ".json",
      "id": "file:inputs/ghl/GHLEmailTemplates__JH4o9LqPhHyuvvyVFJVZ__Latest.json",
      "kind": "file",
      "label": "inputs/ghl/GHLEmailTemplates__JH4o9LqPhHyuvvyVFJVZ__Latest.json",
      "source": "ghl"
    },
    {
      "extension": ".json",
      "id": "file:inputs/ghl/GHLForms__JH4o9LqPhHyuvvyVFJVZ__Latest.json",
      "kind": "file",
      "label": "inputs/ghl/GHLForms__JH4o9LqPhHyuvvyVFJVZ__Latest.json",
      "source": "ghl"
    },
    {
      "extension": ".json",
      "id": "file:inputs/ghl/GHLFunnels__JH4o9LqPhHyuvvyVFJVZ__Latest.json",
      "kind": "file",
      "label": "inputs/ghl/GHLFunnels__JH4o9LqPhHyuvvyVFJVZ__Latest.json",
      "source": "ghl"
    },
    {
      "extension": ".json",
      "id": "file:inputs/ghl/GHLLocation__JH4o9LqPhHyuvvyVFJVZ__Latest.json",
      "kind": "file",
      "label": "inputs/ghl/GHLLocation__JH4o9LqPhHyuvvyVFJVZ__Latest.json",
      "source": "ghl"
    },
    {
      "extension": ".json",
      "id": "file:inputs/ghl/GHLPipelines__JH4o9LqPhHyuvvyVFJVZ__Latest.json",
      "kind": "file",
      "label": "inputs/ghl/GHLPipelines__JH4o9LqPhHyuvvyVFJVZ__Latest.json",
      "source": "ghl"
    },
    {
      "extension": ".json",
      "id": "file:inputs/ghl/GHLTags__JH4o9LqPhHyuvvyVFJVZ__Latest.json",
      "kind": "file",
      "label": "inputs/ghl/GHLTags__JH4o9LqPhHyuvvyVFJVZ__Latest.json",
      "source": "ghl"
    },
    {
      "extension": ".json",
      "id": "file:inputs/ghl/GHLTriggerLinks__JH4o9LqPhHyuvvyVFJVZ__Latest.json",
      "kind": "file",
      "label": "inputs/ghl/GHLTriggerLinks__JH4o9LqPhHyuvvyVFJVZ__Latest.json",
      "source": "ghl"
    },
    {
      "extension": ".json",
      "id": "file:inputs/ghl/GHLUsers__JH4o9LqPhHyuvvyVFJVZ__Latest.json",
      "kind": "file",
      "label": "inputs/ghl/GHLUsers__JH4o9LqPhHyuvvyVFJVZ__Latest.json",
      "source": "ghl"
    },
    {
      "extension": ".json",
      "id": "file:inputs/ghl/GHLWorkflow__82cb0414-c64a-4fdd-8961-96719dea3878__Latest.json",
      "kind": "file",
      "label": "inputs/ghl/GHLWorkflow__82cb0414-c64a-4fdd-8961-96719dea3878__Latest.json",
      "source": "ghl"
    },
    {
      "extension": ".json",
      "id": "file:inputs/ghl/GHLWorkflow__90cecd4e-e701-46bb-87c5-9aa43c2b0ea5__Latest.json",
      "kind": "file",
      "label": "inputs/ghl/GHLWorkflow__90cecd4e-e701-46bb-87c5-9aa43c2b0ea5__Latest.json",
      "source": "ghl"
    },
    {
      "extension": ".json",
      "id": "file:inputs/ghl/GHLWorkflows__JH4o9LqPhHyuvvyVFJVZ__Latest.json",
      "kind": "file",
      "label": "inputs/ghl/GHLWorkflows__JH4o9LqPhHyuvvyVFJVZ__Latest.json",
      "source": "ghl"
    },
    {
      "extension": ".md",
      "id": "file:inputs/ghl/README.md",
      "kind": "file",
      "label": "inputs/ghl/README.md",
      "source": "ghl"
    },
    {
      "extension": ".json",
      "id": "file:inputs/make/MAKE_SCENARIOS.json",
      "kind": "file",
      "label": "inputs/make/MAKE_SCENARIOS.json",
      "source": "make"
    },
    {
      "extension": ".json",
      "id": "file:inputs/make/MAKE_SCENARIO_INDEX__Latest.json",
      "kind": "file",
      "label": "inputs/make/MAKE_SCENARIO_INDEX__Latest.json",
      "source": "make"
    },
    {
      "extension": ".json",
      "id": "file:inputs/make/MAKE_SCENARIO_LISTING__Latest.json",
      "kind": "file",
      "label": "inputs/make/MAKE_SCENARIO_LISTING__Latest.json",
      "source": "make"
    },
    {
      "extension": ".json",
      "id": "file:inputs/make/MakeProbe__Latest.json",
      "kind": "file",
      "label": "inputs/make/MakeProbe__Latest.json",
      "source": "make"
    },
    {
      "extension": ".md",
      "id": "file:inputs/make/README.md",
      "kind": "file",
      "label": "inputs/make/README.md",
      "source": "make"
    },
    {
      "extension": ".json",
      "id": "file:inputs/make/blueprints/MakeBlueprint__2348337__Latest.json",
      "kind": "file",
      "label": "inputs/make/blueprints/MakeBlueprint__2348337__Latest.json",
      "source": "make"
    },
    {
      "extension": ".json",
      "id": "file:inputs/make/blueprints/MakeBlueprint__3664392__Latest.json",
      "kind": "file",
      "label": "inputs/make/blueprints/MakeBlueprint__3664392__Latest.json",
      "source": "make"
    },
    {
      "extension": ".json",
      "id": "file:inputs/make/blueprints/MakeBlueprint__3673026__Latest.json",
      "kind": "file",
      "label": "inputs/make/blueprints/MakeBlueprint__3673026__Latest.json",
      "source": "make"
    },
    {
      "extension": ".json",
      "id": "file:inputs/make/blueprints/MakeBlueprint__3686763__Latest.json",
      "kind": "file",
      "label": "inputs/make/blueprints/MakeBlueprint__3686763__Latest.json",
      "source": "make"
    },
    {
      "extension": ".json",
      "id": "file:inputs/make/blueprints/MakeBlueprint__3686991__Latest.json",
      "kind": "file",
      "label": "inputs/make/blueprints/MakeBlueprint__3686991__Latest.json",
      "source": "make"
    },
    {
      "extension": ".json",
      "id": "file:inputs/make/blueprints/MakeBlueprint__3687011__Latest.json",
      "kind": "file",
      "label": "inputs/make/blueprints/MakeBlueprint__3687011__Latest.json",
      "source": "make"
    },
    {
      "extension": ".json",
      "id": "file:inputs/make/blueprints/MakeBlueprint__3733465__Latest.json",
      "kind": "file",
      "label": "inputs/make/blueprints/MakeBlueprint__3733465__Latest.json",
      "source": "make"
    },
    {
      "extension": ".json",
      "id": "file:inputs/make/blueprints/MakeBlueprint__3738189__Latest.json",
      "kind": "file",
      "label": "inputs/make/blueprints/MakeBlueprint__3738189__Latest.json",
      "source": "make"
    },
    {
      "extension": ".json",
      "id": "file:inputs/make/blueprints/MakeBlueprint__3744510__Latest.json",
      "kind": "file",
      "label": "inputs/make/blueprints/MakeBlueprint__3744510__Latest.json",
      "source": "make"
    },
    {
      "extension": ".json",
      "id": "file:inputs/make/blueprints/MakeBlueprint__3745933__Latest.json",
      "kind": "file",
      "label": "inputs/make/blueprints/MakeBlueprint__3745933__Latest.json",
      "source": "make"
    },
    {
      "extension": ".json",
      "id": "file:inputs/make/blueprints/MakeBlueprint__3761572__Latest.json",
      "kind": "file",
      "label": "inputs/make/blueprints/MakeBlueprint__3761572__Latest.json",
      "source": "make"
    },
    {
      "extension": ".json",
      "id": "file:inputs/make/blueprints/MakeBlueprint__3795815__Latest.json",
      "kind": "file",
      "label": "inputs/make/blueprints/MakeBlueprint__3795815__Latest.json",
      "source": "make"
    },
    {
      "extension": ".json",
      "id": "file:inputs/make/blueprints/MakeBlueprint__3798600__Latest.json",
      "kind": "file",
      "label": "inputs/make/blueprints/MakeBlueprint__3798600__Latest.json",
      "source": "make"
    },
    {
      "extension": ".json",
      "id": "file:inputs/make/blueprints/MakeBlueprint__3818644__Latest.json",
      "kind": "file",
      "label": "inputs/make/blueprints/MakeBlueprint__3818644__Latest.json",
      "source": "make"
    },
    {
      "extension": ".json",
      "id": "file:inputs/make/blueprints/MakeBlueprint__3818650__Latest.json",
      "kind": "file",
      "label": "inputs/make/blueprints/MakeBlueprint__3818650__Latest.json",
      "source": "make"
    },
    {
      "extension": ".json",
      "id": "file:inputs/make/blueprints/MakeBlueprint__3818652__Latest.json",
      "kind": "file",
      "label": "inputs/make/blueprints/MakeBlueprint__3818652__Latest.json",
      "source": "make"
    },
    {
      "extension": ".json",
      "id": "file:inputs/make/blueprints/MakeBlueprint__3818663__Latest.json",
      "kind": "file",
      "label": "inputs/make/blueprints/MakeBlueprint__3818663__Latest.json",
      "source": "make"
    },
    {
      "extension": ".json",
      "id": "file:inputs/make/blueprints/MakeBlueprint__3824254__Latest.json",
      "kind": "file",
      "label": "inputs/make/blueprints/MakeBlueprint__3824254__Latest.json",
      "source": "make"
    },
    {
      "extension": ".json",
      "id": "file:inputs/make/blueprints/MakeBlueprint__3824833__Latest.json",
      "kind": "file",
      "label": "inputs/make/blueprints/MakeBlueprint__3824833__Latest.json",
      "source": "make"
    },
    {
      "extension": ".json",
      "id": "file:inputs/make/blueprints/MakeBlueprint__3859876__Latest.json",
      "kind": "file",
      "label": "inputs/make/blueprints/MakeBlueprint__3859876__Latest.json",
      "source": "make"
    },
    {
      "extension": ".json",
      "id": "file:inputs/make/blueprints/MakeBlueprint__3920516__Latest.json",
      "kind": "file",
      "label": "inputs/make/blueprints/MakeBlueprint__3920516__Latest.json",
      "source": "make"
    },
    {
      "extension": ".json",
      "id": "file:inputs/make/blueprints/MakeBlueprint__3920818__Latest.json",
      "kind": "file",
      "label": "inputs/make/blueprints/MakeBlueprint__3920818__Latest.json",
      "source": "make"
    },
    {
      "extension": ".json",
      "id": "file:inputs/make/blueprints/MakeBlueprint__3952284__Latest.json",
      "kind": "file",
      "label": "inputs/make/blueprints/MakeBlueprint__3952284__Latest.json",
      "source": "make"
    },
    {
      "extension": ".json",
      "id": "file:inputs/make/blueprints/MakeBlueprint__3961170__Latest.json",
      "kind": "file",
      "label": "inputs/make/blueprints/MakeBlueprint__3961170__Latest.json",
      "source": "make"
    },
    {
      "extension": ".json",
      "id": "file:inputs/make/blueprints/MakeBlueprint__3996198__Latest.json",
      "kind": "file",
      "label": "inputs/make/blueprints/MakeBlueprint__3996198__Latest.json",
      "source": "make"
    },
    {
      "extension": ".json",
      "id": "file:inputs/make/blueprints/MakeBlueprint__4001823__Latest.json",
      "kind": "file",
      "label": "inputs/make/blueprints/MakeBlueprint__4001823__Latest.json",
      "source": "make"
    },
    {
      "extension": ".json",
      "id": "file:inputs/make/blueprints/MakeBlueprint__4002164__Latest.json",
      "kind": "file",
      "label": "inputs/make/blueprints/MakeBlueprint__4002164__Latest.json",
      "source": "make"
    },
    {
      "extension": ".json",
      "id": "file:inputs/make/blueprints/MakeBlueprint__4002272__Latest.json",
      "kind": "file",
      "label": "inputs/make/blueprints/MakeBlueprint__4002272__Latest.json",
      "source": "make"
    },
    {
      "extension": ".json",
      "id": "file:inputs/make/blueprints/MakeBlueprint__4055279__Latest.json",
      "kind": "file",
      "label": "inputs/make/blueprints/MakeBlueprint__4055279__Latest.json",
      "source": "make"
    },
    {
      "extension": ".json",
      "id": "file:inputs/make/blueprints/MakeBlueprint__4055283__Latest.json",
      "kind": "file",
      "label": "inputs/make/blueprints/MakeBlueprint__4055283__Latest.json",
      "source": "make"
    },
    {
      "extension": ".json",
      "id": "file:inputs/make/blueprints/MakeBlueprint__4091455__Latest.json",
      "kind": "file",
      "label": "inputs/make/blueprints/MakeBlueprint__4091455__Latest.json",
      "source": "make"
    },
    {
      "extension": ".json",
      "id": "file:inputs/make/blueprints/MakeBlueprint__4091456__Latest.json",
      "kind": "file",
      "label": "inputs/make/blueprints/MakeBlueprint__4091456__Latest.json",
      "source": "make"
    },
    {
      "extension": ".json",
      "id": "file:inputs/make/blueprints/MakeBlueprint__4093385__Latest.json",
      "kind": "file",
      "label": "inputs/make/blueprints/MakeBlueprint__4093385__Latest.json",
      "source": "make"
    },
    {
      "extension": ".json",
      "id": "file:inputs/make/blueprints/MakeBlueprint__4121916__Latest.json",
      "kind": "file",
      "label": "inputs/make/blueprints/MakeBlueprint__4121916__Latest.json",
      "source": "make"
    },
    {
      "extension": ".json",
      "id": "file:inputs/make/blueprints/MakeBlueprint__4123962__Latest.json",
      "kind": "file",
      "label": "inputs/make/blueprints/MakeBlueprint__4123962__Latest.json",
      "source": "make"
    },
    {
      "extension": ".json",
      "id": "file:inputs/make/blueprints/MakeBlueprint__4124710__Latest.json",
      "kind": "file",
      "label": "inputs/make/blueprints/MakeBlueprint__4124710__Latest.json",
      "source": "make"
    },
    {
      "extension": ".json",
      "id": "file:inputs/make/blueprints/MakeBlueprint__4127837__Latest.json",
      "kind": "file",
      "label": "inputs/make/blueprints/MakeBlueprint__4127837__Latest.json",
      "source": "make"
    },
    {
      "extension": ".json",
      "id": "file:inputs/make/blueprints/MakeBlueprint__4128249__Latest.json",
      "kind": "file",
      "label": "inputs/make/blueprints/MakeBlueprint__4128249__Latest.json",
      "source": "make"
    },
    {
      "extension": ".json",
      "id": "file:inputs/make/blueprints/MakeBlueprint__4128593__Latest.json",
      "kind": "file",
      "label": "inputs/make/blueprints/MakeBlueprint__4128593__Latest.json",
      "source": "make"
    },
    {
      "extension": ".json",
      "id": "file:inputs/make/blueprints/MakeBlueprint__4148204__Latest.json",
      "kind": "file",
      "label": "inputs/make/blueprints/MakeBlueprint__4148204__Latest.json",
      "source": "make"
    },
    {
      "extension": ".json",
      "id": "file:inputs/make/blueprints/MakeBlueprint__4185478__Latest.json",
      "kind": "file",
      "label": "inputs/make/blueprints/MakeBlueprint__4185478__Latest.json",
      "source": "make"
    },
    {
      "extension": ".json",
      "id": "file:inputs/make/blueprints/MakeBlueprint__4206316__Latest.json",
      "kind": "file",
      "label": "inputs/make/blueprints/MakeBlueprint__4206316__Latest.json",
      "source": "make"
    },
    {
      "extension": ".json",
      "id": "file:inputs/make/blueprints/MakeBlueprint__4207345__Latest.json",
      "kind": "file",
      "label": "inputs/make/blueprints/MakeBlueprint__4207345__Latest.json",
      "source": "make"
    },
    {
      "extension": ".json",
      "id": "file:inputs/make/blueprints/MakeBlueprint__4226576__Latest.json",
      "kind": "file",
      "label": "inputs/make/blueprints/MakeBlueprint__4226576__Latest.json",
      "source": "make"
    },
    {
      "extension": ".json",
      "id": "file:inputs/make/blueprints/MakeBlueprint__4227392__Latest.json",
      "kind": "file",
      "label": "inputs/make/blueprints/MakeBlueprint__4227392__Latest.json",
      "source": "make"
    },
    {
      "extension": ".json",
      "id": "file:inputs/make/blueprints/MakeBlueprint__4265554__Latest.json",
      "kind": "file",
      "label": "inputs/make/blueprints/MakeBlueprint__4265554__Latest.json",
      "source": "make"
    },
    {
      "extension": ".json",
      "id": "file:inputs/make/blueprints/MakeBlueprint__4267051__Latest.json",
      "kind": "file",
      "label": "inputs/make/blueprints/MakeBlueprint__4267051__Latest.json",
      "source": "make"
    },
    {
      "extension": ".json",
      "id": "file:inputs/make/blueprints/MakeBlueprint__4267120__Latest.json",
      "kind": "file",
      "label": "inputs/make/blueprints/MakeBlueprint__4267120__Latest.json",
      "source": "make"
    },
    {
      "extension": ".json",
      "id": "file:inputs/make/blueprints/MakeBlueprint__4328562__Latest.json",
      "kind": "file",
      "label": "inputs/make/blueprints/MakeBlueprint__4328562__Latest.json",
      "source": "make"
    },
    {
      "extension": ".json",
      "id": "file:inputs/make/blueprints/MakeBlueprint__4347798__Latest.json",
      "kind": "file",
      "label": "inputs/make/blueprints/MakeBlueprint__4347798__Latest.json",
      "source": "make"
    },
    {
      "extension": ".json",
      "id": "file:inputs/make/blueprints/MakeBlueprint__4360004__Latest.json",
      "kind": "file",
      "label": "inputs/make/blueprints/MakeBlueprint__4360004__Latest.json",
      "source": "make"
    },
    {
      "extension": ".md",
      "id": "file:inputs/make/blueprints/README.md",
      "kind": "file",
      "label": "inputs/make/blueprints/README.md",
      "source": "make"
    },
    {
      "extension": ".md",
      "id": "file:inputs/make/digests/MakeDigest__C12IntelReportDigest__3798600__v0.1.json.md",
      "kind": "file",
      "label": "inputs/make/digests/MakeDigest__C12IntelReportDigest__3798600__v0.1.json.md",
      "source": "make"
    },
    {
      "extension": ".md",
      "id": "file:inputs/make/digests/MakeDigest__EmailConveyor__4093385__2026-02-12T15-09-37.json.md",
      "kind": "file",
      "label": "inputs/make/digests/MakeDigest__EmailConveyor__4093385__2026-02-12T15-09-37.json.md",
      "source": "make"
    },
    {
      "extension": ".md",
      "id": "file:inputs/make/digests/MakeDigest__IntelConveyor__4091455__v0.1.json.md",
      "kind": "file",
      "label": "inputs/make/digests/MakeDigest__IntelConveyor__4091455__v0.1.json.md",
      "source": "make"
    },
    {
      "extension": ".md",
      "id": "file:inputs/make/digests/README.md",
      "kind": "file",
      "label": "inputs/make/digests/README.md",
      "source": "make"
    },
    {
      "extension": ".md",
      "id": "file:inputs/models/system/index.md",
      "kind": "file",
      "label": "inputs/models/system/index.md",
      "source": "models"
    },
    {
      "extension": ".md",
      "id": "file:inputs/qb/QB Centurion Intel SEED (1).md",
      "kind": "file",
      "label": "inputs/qb/QB Centurion Intel SEED (1).md",
      "source": "qb"
    },
    {
      "extension": ".md",
      "id": "file:inputs/qb/QB__CenturionIntel__v0.3.md",
      "kind": "file",
      "label": "inputs/qb/QB__CenturionIntel__v0.3.md",
      "source": "qb"
    },
    {
      "extension": ".md",
      "id": "file:inputs/qb/README.md",
      "kind": "file",
      "label": "inputs/qb/README.md",
      "source": "qb"
    },
    {
      "extension": ".md",
      "id": "file:inputs/snapshots/index.md",
      "kind": "file",
      "label": "inputs/snapshots/index.md",
      "source": "snapshots"
    },
    {
      "extension": ".md",
      "id": "file:inputs/softr/README.md",
      "kind": "file",
      "label": "inputs/softr/README.md",
      "source": "softr"
    },
    {
      "extension": ".json",
      "id": "file:inputs/softr/SoftrUsers__Latest.json",
      "kind": "file",
      "label": "inputs/softr/SoftrUsers__Latest.json",
      "source": "softr"
    },
    {
      "extension": ".md",
      "id": "file:inputs/videoask/README.md",
      "kind": "file",
      "label": "inputs/videoask/README.md",
      "source": "videoask"
    },
    {
      "extension": ".json",
      "id": "file:inputs/videoask/VideoAskForms__Latest.json",
      "kind": "file",
      "label": "inputs/videoask/VideoAskForms__Latest.json",
      "source": "videoask"
    },
    {
      "extension": ".md",
      "id": "file:inputs/videopeel/readme.md",
      "kind": "file",
      "label": "inputs/videopeel/readme.md",
      "source": "videopeel"
    },
    {
      "extension": ".md",
      "id": "file:inputs/web/readme.md",
      "kind": "file",
      "label": "inputs/web/readme.md",
      "source": "web"
    }
  ],
  "schema_version": 1
}
